<?xml version="1.0" ?>
<tei xml:space="preserve">
	<teiHeader>
		<fileDesc xml:id="0"/>
	</teiHeader>
	<text xml:lang="hr">










<front>MONNAIES <lb/>

PARIS, HOTEL GEORGE V <lb/>

SALON DE LA PAIX <lb/>

Le Vendredi 25 Mars 1977 <lb/></front>



<annex>Émile BOURGEY <lb/>

Expert National <lb/>

7, rue Drouot, Paris-ge <lb/>

VENTE PUBLIQUE <lb/>

du 25 Mars 1977 <lb/>
Hôtel George V -Salon de la Paix <lb/>

31 avenue George-V, 75008 Paris <lb/>

Tél. 723 54 00 <lb/>

VENTE PUBLIQUE du 25 MARS 1977 <lb/>

BASES D&apos;ÉVALUATIONS <lb/>

EN FRANCS FRANÇAIS <lb/>

SCHATZUNGSPREISE <lb/>
APPROXIMATIVE VALUATIONS <lb/>

No <lb/>

ESTIMATIONS <lb/>
N°E STIMATIONS <lb/>

N°ESTIMATIONS <lb/>

1 <lb/>

1.800/ 2.500 <lb/>

45 <lb/>

6.000/ 8.000 <lb/>

89 <lb/>

2.500/ 3.000 <lb/>

2 <lb/>

1.800/ 2.500 <lb/>

46 <lb/>

2.000/ 3.000 <lb/>

90 <lb/>

1.300/ 1.500 <lb/>

3 <lb/>

18.000/20.000 <lb/>

47 <lb/>

9.000/10.000 <lb/>

91 <lb/>

12.000/15.000 <lb/>

4 <lb/>

12.000/14.000 <lb/>

48 <lb/>

5.000/ 6.000 <lb/>

92 <lb/>

1.200/ 1.500 <lb/>

5 <lb/>

2.500/ 3.000 <lb/>

49 <lb/>

3.000/ 3.500 <lb/>

93 <lb/>

2.400/ 2.800 <lb/>

6 <lb/>

2.500/ 3.000 <lb/>

50 <lb/>

4.500/ 5.500 <lb/>

94 <lb/>

8.000/10.000 <lb/>

7 <lb/>

6.000/ 8.000 <lb/>

51 <lb/>

2.500/ 3.000 <lb/>

95 <lb/>

14.000/18.000 <lb/>

8 <lb/>

2.800/ 3.500 <lb/>

52 <lb/>

1.500/ 2.000 <lb/>

96 <lb/>

10.000/12.000 <lb/>

9 <lb/>

4.500/ 5.500 <lb/>

53 <lb/>

23.000/25.000 <lb/>

97 <lb/>

1.200/ 1.800 <lb/>

10 <lb/>

3.500/ 4.000 <lb/>

54 <lb/>

4.000/ 5.000 <lb/>

98 <lb/>

8.000/ 9.000 <lb/>

11 <lb/>

20.000/25.000 <lb/>

55 <lb/>

10.000/12.000 <lb/>

99 <lb/>

9.000/10.000 <lb/>

12 <lb/>

1.000/ 1.500 <lb/>

56 <lb/>

3.000/ 3.500 <lb/>

100 <lb/>

28.000/35.000 <lb/>

13 <lb/>

3.000/ 3.500 <lb/>

57 <lb/>

6.000/ 7.000 <lb/>

101 <lb/>

7.000/ 9.000 <lb/>

14 <lb/>

25.000/28.000 <lb/>

58 <lb/>

2.500/ 3.500 <lb/>

102 <lb/>

1.000/ 1.200 <lb/>

15 <lb/>

16.000/20.000 <lb/>

59 <lb/>

2.500/ 3.500 <lb/>

103 <lb/>

2.700/ 3.200 <lb/>

16 <lb/>

17.000/20.000 <lb/>

60 <lb/>

9.000/10.000 <lb/>

104 <lb/>

2.000/ 3.000 <lb/>

17 <lb/>

10.000/12.000 <lb/>

61 <lb/>

9.000/10.000 <lb/>

105 <lb/>

8.000/10.000 <lb/>

18 <lb/>

6.000/ 9.000 <lb/>

62 <lb/>

9.000/10.000 <lb/>

106 <lb/>

2.500/ 3.500 <lb/>

19 <lb/>

9.000/11.000 <lb/>

63 <lb/>

8.000/ 9.000 <lb/>

107 <lb/>

400/ 500 <lb/>

20 <lb/>

7.000/ 9.000 <lb/>

64 <lb/>

6.500/ 7.500 <lb/>

108 <lb/>

1.500/ 1.800 <lb/>

21 <lb/>

20.000/25.000 <lb/>

65 <lb/>

3.000/ 4.000 <lb/>

109 <lb/>

1.500/ 2.000 <lb/>

22 <lb/>

9.000/12.000 <lb/>

66 <lb/>

8.000/10.000 <lb/>

110 <lb/>

2.500/ 3.000 <lb/>

23 <lb/>

3.500/ 4.000 <lb/>

67 <lb/>

8.000/10.000 <lb/>

111 <lb/>

15.000/17.000 <lb/>

24 <lb/>

3.500/ 4.000 <lb/>

68 <lb/>

5.000/ 7.000 <lb/>

112 <lb/>

3.500/ 5.000 <lb/>

25 <lb/>

17.000/20.000 <lb/>

69 <lb/>

13.000/15.000 <lb/>

113 <lb/>

8.000/10.000 <lb/>

26 <lb/>

14.000/18.000 <lb/>

70 <lb/>

6.000/ 7.000 <lb/>

114 <lb/>

4.000/ 5.000 <lb/>

27 <lb/>

4.000/ 5.000 <lb/>

71 <lb/>

4.000/ 5.000 <lb/>

115 <lb/>

4.000/ 5.000 <lb/>

28 <lb/>

1.800/ 2.000 <lb/>

72 <lb/>

4.000/ 5.000 <lb/>

116 <lb/>

10.000/12.000 <lb/>

29 <lb/>
3.500&apos;/ 4.000 <lb/>
73 <lb/>

700/ 800 <lb/>

117 <lb/>

5.000/ 7.000 <lb/>

30 <lb/>

10.000/12.000 <lb/>

74 <lb/>

9.000/10.000 <lb/>

118 <lb/>

6.000/ 8.000 <lb/>

31 <lb/>

8.000/10.000 <lb/>

75 <lb/>

3.000/ 3.500 <lb/>

119 <lb/>

5.000/ 7.000 <lb/>

32 <lb/>

2.000/ 2.500 <lb/>

76 <lb/>

7.000/ 8.000 <lb/>

120 <lb/>

4.000/ 6.000 <lb/>

33 <lb/>

3.000/ 3.500 <lb/>

77 <lb/>

7.000/ 8.000 <lb/>

121 <lb/>

4.000/ 5.000 <lb/>

34 <lb/>

3.000/ 3.500 <lb/>

78 <lb/>

3.000/ 4.000 <lb/>

122 <lb/>

12.000/14.000 <lb/>

35 <lb/>

1.500/ 2.000 <lb/>

79 <lb/>

4.000/ 5.000 <lb/>

123 <lb/>

11.000/12.000 <lb/>

36 <lb/>

4.500/ 6.000 <lb/>

80 <lb/>

6.000/ 7.000 <lb/>

123a <lb/>

6.000/ 8.000 <lb/>

37 <lb/>

10.000/12.000 <lb/>

81 <lb/>

4.500/ 5.500 <lb/>

124 <lb/>

6.500/ 8.000 <lb/>

38 <lb/>

4.000/ 5.000 <lb/>

82 <lb/>

4.000/ 4.500 <lb/>

124a <lb/>

2.000/ 2.500 <lb/>

39 <lb/>

3.000/ 4.000 <lb/>

83 <lb/>

2.700/ 3.500 <lb/>

125 <lb/>

3.000/ 3.500 <lb/>

40 <lb/>

3.000/ 4.000 <lb/>

84 <lb/>

5.000/ 5.500 <lb/>

126 <lb/>

3.000/ 3.500 <lb/>

41 <lb/>

1 SOO/ 2.000 <lb/>
85 <lb/>

1.000/ 1.500 <lb/>

127 <lb/>

1.000/ 1.500 <lb/>

42 <lb/>

3.000/ 3.500 <lb/>

86 <lb/>

1.800/ 2.500 <lb/>

128 <lb/>

40.000/45.000 <lb/>

43 <lb/>

1.000/ 1.500 <lb/>

87 <lb/>

3.000/ 4.000 <lb/>

129 <lb/>

6.000/ 8.000 <lb/>

44 <lb/>

7.000/ 8.000 <lb/>

88 <lb/>

9.000/10.000 <lb/>

130 <lb/>

19.000/25.000 <lb/>


N°ESTIMATIONS <lb/>

N°ESTIMATIONS <lb/>

No <lb/>

ESTIMATIONS <lb/>

131 <lb/>

3.500/ 4.500 <lb/>

170 <lb/>

5.000/ 6.000 <lb/>

209 <lb/>

6.800/ 8.000 <lb/>

132 <lb/>

18.000/25.000 <lb/>

171 <lb/>

7.000/ 9.000 <lb/>

210 <lb/>

6.600/ 7.500 <lb/>

133 <lb/>

11.000/13.000 <lb/>

172 <lb/>

6.000/ 9.000 <lb/>

211 <lb/>

8.500/10.000 <lb/>

134 <lb/>

7.000/ 8.000 <lb/>

173 <lb/>

1.200/ 1.500 <lb/>

212 <lb/>

1.800/ 2.500 <lb/>

135 <lb/>

4.500/ 6.000 <lb/>

174 <lb/>

500/ 700 <lb/>

213 <lb/>

1.200/ 1.500 <lb/>

136 <lb/>

9.000/11.000 <lb/>

175 <lb/>

1.500/ 1.800 <lb/>

214 <lb/>

1.500/ 2.000 <lb/>

137 <lb/>

2.000/ 3.000 <lb/>

176 <lb/>

2.500/ 3.000 <lb/>

215 <lb/>

1.200/ 1.500 <lb/>

138 <lb/>

11.000/13000 <lb/>

177 <lb/>

700/ 1.000 <lb/>

216 <lb/>

2.000/ 2.500 <lb/>

139 <lb/>

10.000/12.000 <lb/>

178 <lb/>

1.500/ 1.800 <lb/>

217 <lb/>

4.000/ 4.500 <lb/>

140 <lb/>

5.000/ 7.000 <lb/>

179 <lb/>

2.000/ 2.500 <lb/>

218 <lb/>

12.000/15.000 <lb/>

141 <lb/>

7.000/ 9.000 <lb/>

180 <lb/>

800/ 1.000 <lb/>

219 <lb/>

2.000/ 3.000 <lb/>

142 <lb/>

4.000/ 5.000 <lb/>

181 <lb/>

7.000/ 8.000 <lb/>

220 <lb/>

2.000/ 3.000 <lb/>

143 <lb/>

8.000/ 9.000 <lb/>

182 <lb/>

3.500/ 4.500 <lb/>

221 <lb/>

1.800/ 2.500 <lb/>

144 <lb/>

3.000/ 4.000 <lb/>

183 <lb/>

2.500/ 3.000 <lb/>

222 <lb/>

15.000/20.000 <lb/>

145 <lb/>

7.000/ 9.000 <lb/>

184 <lb/>

1.000/ 1.500 <lb/>

223 <lb/>

4.000/ 5.000 <lb/>

146 <lb/>

4.000/ 5.000 <lb/>

185 <lb/>

3.800/ 4.500 <lb/>

224 <lb/>

4.000/ 5.000 <lb/>

147 <lb/>

1.000/ 1.400 <lb/>

186 <lb/>

1.300/ 1.600 <lb/>

225 <lb/>

5.000/ 7.000 <lb/>

148 <lb/>

4.500/ 5.500 <lb/>

187 <lb/>

1.800/ 2.200 <lb/>

226 <lb/>

2.800/ 3.500 <lb/>

149 <lb/>

1.300/ 1.600 <lb/>

188 <lb/>

400/ 500 <lb/>

227 <lb/>

1.500/ 2.000 <lb/>

150 <lb/>

8.000/ 9.000 <lb/>

189 <lb/>

2.000/ 2.400 <lb/>

228 <lb/>

3.000/ 4.000 <lb/>

151 <lb/>

3.000/ 4.500 <lb/>

190 <lb/>

800/ 1.200 <lb/>

229 <lb/>

2.000/ 3.000 <lb/>

152 <lb/>

2.700/ 3.200 <lb/>

191 <lb/>

800/ 1.200 <lb/>

230 <lb/>

3.200/ 3.800 <lb/>

153 <lb/>

4.000/ 5.000 <lb/>

192 <lb/>

2.000/ 2.200 <lb/>

231 <lb/>

2.800/ 3.500 <lb/>

154 <lb/>

400/ 600 <lb/>

193 <lb/>

2.800/ 3.500 <lb/>

232 <lb/>

1.500/ 2.000 <lb/>

155 <lb/>

1.500/ 2.000 <lb/>

194 <lb/>

1.200/ 1.500 <lb/>

233 <lb/>

15.000/20.000 <lb/>

156 <lb/>

1.500/ 2.000 <lb/>

195 <lb/>

3.500/ 4.000 <lb/>

234 <lb/>

1.600/ 2.000 <lb/>

157 <lb/>

15.000/20.000 <lb/>

196 <lb/>

3.000/ 3.500 <lb/>

235 <lb/>

1.200/ 1.500 <lb/>

158 <lb/>

4.500/ 5.000 <lb/>

197 <lb/>

3.500/ 4.000 <lb/>

236 <lb/>

2.000/ 2.500 <lb/>

159 <lb/>

6.000/ 7.000 <lb/>

198 <lb/>

1.300/ 1.800 <lb/>

237 <lb/>

8.000/ 9.000 <lb/>

160 <lb/>

4.500/ 5.500 <lb/>

199 <lb/>

400/ 600 <lb/>

238 <lb/>

2.800/ 3.500 <lb/>

161 <lb/>

4.000/ 5.000 <lb/>

200 <lb/>

1.500/ 2.000 <lb/>

239 <lb/>

4.000/ 5.000 <lb/>

162 <lb/>

1.800/ 2.500 <lb/>

201 <lb/>

1.500/ 2.000 <lb/>

240 <lb/>

2.000/ 3.000 <lb/>

163 <lb/>

8.000/10.000 <lb/>

202 <lb/>

1.200/ 1.800 <lb/>

241 <lb/>

9.500/11.000 <lb/>

164 <lb/>

8.000/10.000 <lb/>

203 <lb/>

800/ 1.200 <lb/>

242 <lb/>

600/ 900 <lb/>

165 <lb/>

9.000/11.000 <lb/>

204 <lb/>

1.800/ 2.500 <lb/>

243 <lb/>

700/ 1.000 <lb/>

166 <lb/>

3.000/ 4.000 <lb/>

205 <lb/>

1.200/ 1.500 <lb/>

244 <lb/>

1.000/ 1.200 <lb/>

167 <lb/>

1.000/ 1.200 <lb/>

206 <lb/>

1.000/ 1.500 <lb/>

245 <lb/>

800/ 1.000 <lb/>

168 <lb/>

2.800/ 3.500 <lb/>

207 <lb/>

1.800/ 2.500 <lb/>

246 <lb/>

1.200/ 1.500 <lb/>

169 <lb/>

1.000/ 1.500 <lb/>

208 <lb/>

7.000/ 9.000 <lb/>
246a <lb/>

400/ 500 <lb/>


M. Emile BOURGEY <lb/>

Expert en Monnaies et Médailles <lb/>

7 rue Drouot <lb/>

75009 PARIS <lb/>

.. j <lb/>

N°1 <lb/>
F <lb/>

] <lb/>

N°F <lb/>

1 <lb/>

N°11 <lb/>

1 j <lb/>

1.700 j <lb/>
52 j 1.200 j 102 i <lb/>

2 » <lb/>

1.800 1 <lb/>
53 i 20.000 i 103 i <lb/>

3 <lb/>

1 <lb/>

14.500 ! <lb/>
54 ! 3.300 ! 104 ! <lb/>
4 ! 10.000 ! <lb/>
55 ! 10.500 ! 105 j <lb/>

5 ! <lb/>

2.700 ! <lb/>
56 ! 3.500 ! 106 j <lb/>

6 ! <lb/>

2.200 ! <lb/>
57 ! 7.500 I 107 j <lb/>

7 ! <lb/>

4.800 î <lb/>

58 <lb/>

2.100 1 108 | <lb/>

8 ! <lb/>

2.200 ] <lb/>
59 j 2.100 j 109 j <lb/>

9 : <lb/>

3.500 | <lb/>
60 [ 9.000 J 111 | <lb/>

10 [ <lb/>

3.500 | <lb/>
61 | 7.100 1, 112 j <lb/>
11 Il 20.100 j <lb/>
62 11 11.500 j 113 j <lb/>

12 j <lb/>
700 <lb/>

63 1 9.500 j 114 j <lb/>

13 j <lb/>

2.700 j <lb/>
64 | 5.500&apos; j 115 [ <lb/>
141 20.000 « <lb/>

65, 2.800 1 116 i <lb/>

15&apos; <lb/>

! <lb/>

13.000 ! <lb/>
66 1 6.500 1 117 ! <lb/>
16: 12.000 ! <lb/>

6711 <lb/>

8.00011 lis! <lb/>

17 ! <lb/>

7.000 ! <lb/>
68 ! 4.500 ! 119 ! <lb/>
18i 7.500 ! <lb/>

69 ! 10.000: i2°! <lb/>

1911 <lb/>

ll.ooo! 70: 4.800 ! 121 J <lb/>

20 l&apos; <lb/>

6.500! 7111 2.800 | 122 | 11 <lb/>


M. Emile BOURGEY <lb/>

Expert en Monnaies et Médailles <lb/>

7 rue Drouot <lb/>

75009 PARIS <lb/>

VENTE j3u_25J4ars_1977 <lb/>

PRIX D &apos;ADJUDICATION <lb/>

1 <lb/>

11 <lb/>

il il 11 <lb/>

N°1 <lb/>

F <lb/>

1 <lb/>

N°F <lb/>

1 <lb/>

N°1 <lb/>

F j <lb/>

N°] <lb/>

F <lb/>

j <lb/>

N°F <lb/>

111 <lb/>

1.700 1 <lb/>

52 <lb/>

! <lb/>

1.200 » 102 ! 1.300 ! 152 ! 2.300 1 204 ! <lb/>
2.750 <lb/>

2 1 <lb/>

1.800 » <lb/>

53 <lb/>

&apos; 20.000 » 103 ! 3.200 ! 153 ! 4.200 ! 205 <lb/>
1.400 <lb/>

3i 14.500 ! 54i 3.300 i 14101 2.200 1 154! <lb/>

700 i 206 ! <lb/>

1.300 <lb/>

4! 10.000 ! <lb/>
55! 10.50011 105 j 7.800 j 155 ! 3.400 ! 207 ! <lb/>

2.800 <lb/>

5! 2.700 ! <lb/>

56 ! 3.50011 1061 300011 156! 1.700 ! 208 ! <lb/>
8.500 <lb/>

6 ! <lb/>

2.200 ! <lb/>

57Î 7.500: 107 ! <lb/>

800 ! 157 ! 14.000 ! 209 ! <lb/>
8.500 <lb/>

7Î 4.800 ! <lb/>
58! 2.100: 108] 2.000j 158 ! 4.000 ! 210 \ 7.500 <lb/>
8! 2.200 ! <lb/>
59! 2.100: 109 ! 1.500 ! 159} 5.000 j 211 ! 10.500 <lb/>

911 <lb/>

3.500il <lb/>

60 [ 9.000il 111 j 19.000 Il 160 | 3.800 : 212 ] <lb/>
3.100 <lb/>

10: <lb/>

3.50011 <lb/>

6111 7.1001, 112 J 5.000: 161 j 3.200 : 213 j 1.300 <lb/>

11 j 20.100 ! <lb/>
621. 11.500 | 113 j 12.000 j 162 Il 1.500 Il 214 j <lb/>
1.000 <lb/>
12&quot; <lb/>

700 1 <lb/>

631 <lb/>

9.5001 114 1 5.500 1 163 7.500 1 215 » 2.400 <lb/>

13&apos; 2.700 1 <lb/>
641 5.5001 115 ! 5.500 ! 164! 7.500 ! 216 ! <lb/>

2.900 <lb/>
141 20.000 » <lb/>

65 <lb/>

î <lb/>

2.800 1 116 1 11.000 ! 165 ! 7.000 ! 217 ! <lb/>
5.000 <lb/>
15 I 13.000 Il <lb/>

661 651, <lb/>

6.50011 <lb/>

117 ! 6.000 1 166! 2.500 ! 218 ! 13.000 <lb/>
16! 12.000 1 <lb/>

6711 <lb/>

8.00011 <lb/>

118 ! 6.500 il 167 ! 1.750 ! 219 ! <lb/>
3.700 <lb/>

171 <lb/>
7.0001 <lb/>

681&apos; <lb/>

4.500: 119 ! 4.800: 168l&apos; 2.500 ! 220 ! <lb/>

2.500 <lb/>

18 ! <lb/>

7.500: <lb/>
69: lo.oooll 120 j 3.500: 169j <lb/>
900 ! 221J <lb/>

2.100 <lb/>

19, 11.000: <lb/>
70: 4.800 ! 121 [ 4.000] 171 j 6.200 j 222 [ 27.000 <lb/>

201 <lb/>

6.500 [ <lb/>
71: 2.800 j 122 j 16.000 j 172 j 5.200 j 223 j <lb/>
5.500 <lb/>

21l&apos; <lb/>

16.000] <lb/>
72j 2.6001 123 112.000Il 173] 1.200 ] 224] <lb/>

2.500 <lb/>

2211 <lb/>

11.600 [ <lb/>

731, <lb/>

1.100 | 123Aj 4.800] 174] <lb/>

800 j 225 [ <lb/>

6.800 <lb/>

2311 <lb/>

3.500 Il <lb/>
741 7.0001 124 1 5.800 1 175 » 2.000 » 226 » <lb/>
2.200 <lb/>

24 3.500 » 751 3.000 124Ai 1 2.800 1 176 ! 2.100 ! 227 ! 2.000 <lb/>
25 14.000 » 76 i 5.0001 125 ! 3.500 ! 177 ! <lb/>

700 ! 228 ! <lb/>

3.600 <lb/>

26 <lb/>

i <lb/>

12.000 1 <lb/>

7611 77 <lb/>

4.2001 127 ! <lb/>

90011 <lb/>

178! 2.300 ! 229 ! <lb/>

6.500 <lb/>
27! <lb/>
2.800 ! <lb/>

78! 3.200.1 128 ! 50.000 ! 179! 1.700 ! 230 ! <lb/>
7.500 <lb/>
28! <lb/>

1.300! <lb/>

79! 4.0001 129! 6.800 j 180 ! 1.400 ! 231 ] <lb/>
5.200 <lb/>
29! <lb/>

2.500: <lb/>

80: 4.500&apos;1 130 j 19.000 | 181 ! 7.000 ! 232 [ <lb/>
4.000 <lb/>

3o! 12.000: <lb/>
81 ! 3.300: 131 ! 3.200] 182] 3.500 ] 233 j 23.000 <lb/>

311 <lb/>

6.500! <lb/>
82: 3.000Î 132 [12.000] 183] 3.200 j 234] <lb/>

2.700 <lb/>
32[ <lb/>
2.000 <lb/>
83! 2.400 [ 133 [ 10.500 j 184] 1.800 j 235 j <lb/>
1.300 <lb/>
33] <lb/>
3.200 [ <lb/>

841, <lb/>

5.60011 134] 7.500: 185] 4.800 ] 236 [ <lb/>

2.700 <lb/>

341, <lb/>

2.500 il <lb/>

8511 <lb/>

90011 <lb/>

135] 5.20011 186] 2 .000 <lb/>

237 <lb/>

8.000 <lb/>

3511 <lb/>

1.500 j <lb/>

8611 <lb/>

1.200 J 135iV 2.500 1 187 » 2.200 » 238 <lb/>
2.800 <lb/>

361 <lb/>

4.200 » <lb/>

8711 <lb/>

2.0001 136 i 11.000 ! 188 ! <lb/>
700 ! 239 20.500 <lb/>

371 <lb/>

7.000 » <lb/>
881 8.800, 137 ! 3.000 ! 189! 2.300 ! 240 ! <lb/>
3.000 <lb/>

38 <lb/>

i <lb/>

3.000 ! <lb/>
89: 3.000: 138! 11.000 <lb/>

190 ! <lb/>
810 ! 241 \ <lb/>

6.000 <lb/>
39: <lb/>
2.500 ! <lb/>
90: 2.000! 139! 12.500 j 191: 1.700 ! 242 ! <lb/>

600 <lb/>

40 ! <lb/>

2.900 ! <lb/>
91: 10.500: 140 ! 4.000il 192! 2.400 \ 243 ] <lb/>

600 <lb/>

411 <lb/>

1.400: <lb/>

92! <lb/>

800 ! 141 | 5.000 ] 194: 2.000 \ 244] <lb/>

500 <lb/>

421 <lb/>

2.800 ! <lb/>

93! 2.500! 142] 3.100] 195 j 6 .000 | 245 j <lb/>

1.000 <lb/>

4311 <lb/>

1.300: <lb/>

94,&apos; <lb/>

8.000: 143] 10.500Il 196] 4.500 j 246 j <lb/>
1.300 <lb/>
44] <lb/>

8.500] <lb/>

95] 16.800: 144 [ 2.200 [ 197 j 6.000 j 246AI1 <lb/>

150 <lb/>

45: <lb/>

7.600li <lb/>

961, <lb/>

8.5001, 145] 8.000Il 198] 1.400 » <lb/>

j <lb/>

46] <lb/>

2.60011 <lb/>

9711 <lb/>

2.50011 146] 2.200.1 199:1 1.050 1 <lb/>



47 j <lb/>

7.000 <lb/>

98&apos; 8.8001 147 1 <lb/>
900 1 200 1 2.300 1 <lb/>



491 <lb/>

2.300 <lb/>

991 <lb/>

11.00011 <lb/>

148.1 <lb/>

3.800 ! 201 ! 1.300 ! <lb/>

! <lb/>

50&apos; <lb/>
2.600 1, 1 1001 30.500! 149! 1.100! 20211 1.500 ! <lb/>

! <lb/>

5111 <lb/>

3.20011 <lb/>

loi: 9.80011 151! 2.00011 20311 1.100 ! <lb/>

! <lb/>

I <lb/>

II II II II <lb/>

I <lb/>

II II II II <lb/>

I <lb/>

II II II II <lb/>

I <lb/>

II II I • • « <lb/></annex>



<front>MONNAIES <lb/>

GRECQUES -ROMAINES <lb/>
BYZANTINES -GAULOISES <lb/>
FRANÇAISES <lb/>

-<lb/>

FÉODALES <lb/>
ÉTRANGÈRES <lb/>

dont la vente aux enchères publiques aura lieu <lb/>

HOTEL GEORGE V, SALON DE LA PAIX <lb/>

31, avenue George V, 75008 PARIS -Tél. 723.54.00 <lb/>

Le Vendredi 25 Mars 1977 à 14 h 15 <lb/>

par le ministère de : <lb/>
Me Etienne ADER <lb/>
Me Antoine ADER <lb/>

12, rue Favart -75002 PARIS -Tél. 742-68-23 <lb/>

assistés de : <lb/>

M. Émile BOURGEY <lb/>

Expert National près les Cours d&apos;Appel et les Douanes <lb/>

7, rue Drouot, 75009 Paris (770-88-67 et 770-35-18) <lb/>

EXPOSITION PUBLIQUE <lb/>
Le Jeudi 24 Mars de 14 h 30 à 18 h <lb/>
-Salon de la Paix <lb/>
EXPOSITION PRIVÉE <lb/>
chez M. Émile Bourgey 7, rue Drouot, du 14 au 22 Mars 1977 <lb/>

(jours ouvrables) <lb/>


CONDITIONS DE LA VENTE <lb/>

La vente aura lieu au comptant. <lb/>

Les acquéreurs paieront, en sus des enchères pour chaque lot adjugé : <lb/>

16,00 pour cent jusqu&apos;à 6 000 F ; <lb/>
11,50 pour cent de 6 001 à 20 000 F ; <lb/>
10,00 pour cent au-dessus de 20 000 F. <lb/>

M. Emile BOURGEY se charge d&apos;exécuter les ordres d&apos;achats qui lui <lb/>
seront confiés, sans frais. (Formulaire ci-inclus). Tél. : 770-88-67 et 35-18. <lb/>

Les numéros 230, 231 seront inscrits sur le Procès-Verbal de Mc Offret, Commis-<lb/>

saire-Priseur à Paris. <lb/>

Les conditions de vente sont celles régies par la réglementation française <lb/>
concernant les ventes publiques. <lb/>

CONDITIONS OF SALE <lb/>

Full cash settlement of the purchases will be required. <lb/>
In addition to the sale price, the buyers will have to pay the following char-<lb/>
ges for each individual purchase : <lb/>
16.00 per cent up to 6,000 F. <lb/>
11.50 per cent from 6,001 up to 20,000 F. <lb/>
10.00 per cent over 20,000 F. <lb/>
Bids may be placed through Mr. Emile BOURGEY, by using the enclosed order <lb/>
blank. Tel : 770-88-67 et 35-18. <lb/>

Nos 230, 231 will be registered on Mc Offret&apos;s auction official record. <lb/>
The conditions of sale*are subject to existing French regulations regarding <lb/>

public auctions. <lb/>

ETATS DE CONSERVATION <lb/>

indiqués <lb/>

F.D.C. : Fleur de Coin <lb/>

10/10 <lb/>

Superbe ou Splendide <lb/>

8 à 9/10 <lb/>

Très Beau <lb/>

6 à 7/10 <lb/>

T.B. <lb/>

4 à 5/10 <lb/>
B./T.B. <lb/>
2 à 3/10 <lb/>

SCALE DESCRIBING THE CONDI-<lb/>
TION OF THE COINS : <lb/>

Mint State <lb/>

10/10 <lb/>

Extremely Fine or <lb/>

Splendid <lb/>

8 -9/10 <lb/>
Very Fine <lb/>
6 -7/10 <lb/>
Fine <lb/>
4 -5/10 <lb/>

Fair <lb/>

2 -3/10 <lb/>

Les numéros reproduits sur les planches sont précédés d&apos;un astérisque. <lb/>
The numbers identified with an asterisk are illustrated on the plates. <lb/>


La place toute particulière prise par les Monnaies Grecques auprès <lb/>
des collectionneurs, au fil de ces dernières années, est due, pour une grande <lb/>
part, à la richesse de l&apos;esthétique que l&apos;on découvre sur ces petits monu-<lb/>
ments de l&apos;art antique, qui se déploie à travers les différents types adoptés <lb/>
par chaque ville, chaque cité autonome depuis l&apos;époque archaïque jusqu&apos;à <lb/>

la domination romaine. La recherche de la beauté, le souci de l&apos;harmonie <lb/>
en sont la motivation permanente qui démontre le sens artistique des <lb/>

Grecs jusque dans ce domaine de la vie quotidienne. <lb/>
Demi-statère en or de Tarente, Tétradrachmes de Rhégium, d&apos;Himéra, <lb/>
de Léontion, de Messine ou de Syracuse, précèdent les Statères de Macé-<lb/>

doine, de Thrace à travers toute la Grèce classique, l&apos;Asie Mineure ou <lb/>
l&apos;Egypte, dans cet ensemble de près de cent exemplaires qui forme un <lb/>
choix particulièrement attrayant. <lb/>

Quelques monnaies romaines, dont un très bel Aureus de Julia Domna, <lb/>
cette jeune Syrienne devenue Impératrice et l&apos;épouse de Septime Sévère <lb/>

grâce à son seul horoscope et à la puissance de l&apos;astrologie en cette fin <lb/>
du deuxième Siècle de notre ère, seront ensuite proposées. <lb/>
Les monnaies françaises présentent, en dehors de quelques monnaies <lb/>
gothiques, un très beau spécimen du Double Henri d&apos;or à l&apos;effigie d&apos;Henri II, <lb/>

de l&apos;atelier de Toulouse, puis une série assez remarquable des différents <lb/>
types de Louis du XVIIe au XVIIIe Siècle, aux effigies variées et d&apos;une <lb/>
iconographie souvent remarquable, telle cette monnaie à l&apos;effigie de <lb/>
Louis XV enfant, frappée en 1718 pendant la Régence, appelée usuellement <lb/>

Louis « à la Croix de Malte », bien que certains documents de l&apos;époque le <lb/>
dénomment « à la Croix du Saint Esprit. » <lb/>
Parmi les monnaies féodales, un exemplaire particulièrement intéres-<lb/>
sant de François II de Bretagne, frappé à Nantes, montre le Duc de Breta-<lb/>
gne, armé de toutes pièces, visière baissée galopant sur un cheval capara-<lb/>

çonné orné d&apos;hermines. L&apos;on sait que François II, mort en 1488, fut le der-<lb/>
nier duc à frapper monnaie aux armes de Bretagne, sa fille Anne ayant <lb/>
épousé successivement Charles VIII, puis Louis XII, rattachant ainsi son <lb/>

fief au royaume de France. <lb/>
Une autre monnaie d&apos;or, mais celle-ci de Savoie, d&apos;un type iconogra-<lb/>
phique assez semblable, frappé par Louis Ier, entre 1434 et 1465, Ducat <lb/>
d&apos;or, provenant de l&apos;un des quatre ateliers en activité à cette époque, soit : <lb/>

Annecy, Bourg en Bresse, Cornavin ou Turin, illustre, à travers quelques <lb/>
exemplaires d&apos;Espagne, de la Principauté de Monaco ou de la Confédéra-<lb/>
tion Helvétique, la dernière partie de cette Vente. <lb/>

E. B. <lb/></front>



<body>MONNAIES GRECQUES <lb/>

(en argent sauf indication contraire) <lb/>

ITALIE <lb/>

*1 -CAMPANIE. NAPLES. (325-280). Didrachme. Tête de femme diadémée à d. Derrière, une sta-<lb/>
tuette d&apos;Artémis courant à d. et tenant un flambeau. R/. Taureau androcéphale à d., couronné <lb/>
par une Victoire. A l&apos;exergue : NEOIIOAITQN. (Sambon 466 var. -British Museum Coins 80 <lb/>

var. p. 102 -Pozzi 90 var.). 7 g 21. T.B. <lb/>

*2 -(Après 300-241). Didrachme. Même effigie à g. R/. Même type à g. (S. voir 483 -B.M.C. voir <lb/>

88 p. 103). 7 g 45. T.B. <lb/>

*3 ---CALABRE. TARENTE. (Vers 281). Demi statère. Tête d&apos;Héraclès imberbe à d., coiffée de la <lb/>

peau de lion. R/. Bige au galop à d., conduit par Taras nu, armé d&apos;un trident. A l&apos;exergue : TARAN-<lb/>

T!NHN. (Vlasto voir 29 sq. -S.N.G. Lloyd voir 201). Or. 4 g 33. Sauf léger coup sur la tranche, <lb/>
Très Beau à Superbe. Très Rare. <lb/>

*4 -(Vers 520-500). Didrachme. Taras nu chevauchant un dauphin à g. Derrière : TAR; dessous, un <lb/>
pétoncle. Au pourtour, cercle très épais. R/. Roue à quatre rais dans un cercle très épais. (V. 89 <lb/>

-S.N.G. München 599 var.). 7 g 91. Mince éclat du flan. Très Beau. Rare. <lb/>

*5 -(272-235). Statère. Cavalier nu au pas à g., couronnant son cheval. Derrière, monogramme des <lb/>

lettres N et K, dessous : OIAOKPA. R/. Taras nu, chevauchant un dauphin à g., tenant un can-<lb/>

thare et un trident. Derrière : ATTOA, dessous : TARAS. (V. 831). 6 g 23. Bien centré. Très Beau. <lb/>


*6 <lb/>

LUCANIE. METAPONTE. (550-510). Statère. Epi de blé. A d. : META. Au pourtour, une <lb/>
bande circulaire perlée. R/. Même type incus. (B.M.C. 9 var. p. 238 -Babelon 1, 2061 var. -<lb/>
S.N.G. Lloyd 299 var.). 7 g 74. Légère corrosion partielle. T.B. <lb/>

*7 -(330-300). Statère. Tête de Déméter à g., couronnée d&apos;épis, les cheveux retombant sur la nuque. <lb/>
R/. Epi de blé avec une feuille à g. Dans le champ, tenailles et... A à g. et META à d. (B.M.C. <lb/>
106 p. 252 -S.N.G. ANS. 458). 7 g 86. Beau style. Très Beau. <lb/>

*8 -Statère. Même type. R/. Même type, mais dans le champ, fourche et... A à g. et META à de <lb/>
(S.N.G. Oxford 756 -S.N.G. München 994). 7 g 88. T.B./Très Beau. <lb/>

*9 -BRUTTIUM. CROTONE. (550-480). Statère. Trépied sur une base. A g. : OP?. Au pourtour, <lb/>

une bande circulaire perlée. R/. Aigle en creux, volant à d., les ailes éployées. (B.M.C. 35 var&apos;. <lb/>

p. 345 -Bab. I, 2167 var.). 7 g 99. T.B. <lb/>

4 <lb/>

*10 -(420-390). Statère. Aigle debout à g. sur un rameau d&apos;olivier, les ailes éployées. R/. Trépied, à <lb/>
g. : KPO; à d. : une cigogne et A. (B.M.C. 78 p. 352 -P. 298). 7 g 74. Bel exemplaire bien centré. <lb/>

*11 -RHEGIUM. (466-415). Tétradrachme. Masque de lion de face. Dans le champ à g., un rameau <lb/>
d&apos;olivier avec son fruit, à d., un lièvre courant. R/. RECIIII/O. Iocaste demi-nu, assis à g. et s&apos;ap-<lb/>
puyant sur un bâton, tenant un canthare de la main d. Derrière le siège, un oiseau. Au pourtour, <lb/>

une couronne de laurier. (Herzfelder 56 f = Hess 207, 114 = Collection Pozzi : Naville 1,322 <lb/>

= Seltman, N.C. 1897, pl. VIII, 4 cet exemplaire). 17 g 15. Très Beau/T.B. Rare. <lb/>
Vraisemblablement, exemplaire de la collection Pozzi n°322. ( Llicerne, 4 avril 1921 -270 fr. ss). <lb/>


SICILE <lb/>

*12 -AGRIGENTE. (413-406). Hémidrachme. Aigle debout à g., les ailes éployées, dévorant un lièvre. <lb/>
R/. AKPA. Crabe; au-dessous, un poisson. (B.M.C. 68 p. 13 -Jameson 515). 2 g 08. T.B. <lb/>

*13 -GELA. (Avant 466). Didrachme. Cavalier au galop à d., coiffé du pilos et brandissant une lance. <lb/>

R/. Le fleuve Gélas, sous la forme d&apos;un taureau à tête humaine barbue, à d. Dessous : CEAAS. <lb/>

(B.M.C. 17 p. 67 -S.N.G. Lockett 759). 8 g 16. Bien centré. T.B. <lb/>

*14 -HIMERA. (472-413). Tétradrachme. La nymphe Himera drapée, debout, sacrifiant à g. sur un <lb/>

autel. A d. Silène nu, debout dans un bassin, sous le jet d&apos;une fontaine en gueule de lion. Grain <lb/>
d&apos;orge au-dessus du bras g. R/. Quadrige au pas à d.; Niké volant à g. couronne l&apos;aurige. A l&apos;exer-<lb/>

gue, traces de l&apos;inscription rétrograde : MEPAION. (B.M.C. 33 p. 79 -P. 456 -S.N.G. Lockett <lb/>
787). 17 g 26. Bel exemplaire. Très Rare. <lb/>

*15 -LEONTION. (500-466). Tétradrachme. Personnage dans un quadrige au galop à d. Niké volant <lb/>
à d., couronne les chevaux. R/. AEONTINON en légende rétrograde. Tête de lion à d., la gueule <lb/>

béante. Au pourtour quatre grains d&apos;orge. (B.M.C. 6 var. p. 86 -Bab. I, 2228 var. -S.N.G <lb/>

Lockett 790 var.). 17 g. 36. Très Beau. De très belle qualité. <lb/>

*16 -MESSINE. (461-396). Tétradrachme. Bige de mules au pas à g. (Sans Niké). A l&apos;exergue, deux <lb/>

dauphins affrontés. R/. Lièvre courant à g.; au-dessus un aigle; au-dessous un épi de blé. A l&apos;exer-<lb/>
gue : MESSANION. (B.M.C. 46 var. p. 104 -J. 657 -S.N.G. Lockett 831 var.). 17 g 14. Flan <lb/>

large. Très Beau. <lb/>

*17 -SELINONTE. (466-415). Didrachme. EE-AklOTIOlol. Héraclès nu, brandissant sa massue et arrê-<lb/>
tant par la corne un taureau bondissant à d. R/. HYVA2. Le fleuve Hypsas nu, debout de face, <lb/>

sacrifiant sur un autel à g. et tenant un rameau d&apos;olivier. A d., feuille de persil et héron. (B.M.C. <lb/>
34 p. 141 -S.N.G. Lockett *X64). 8 g 45. Bel exemplaire. Rare. <lb/>

*18 -SYRACUSE. Tyrannie de Dionysos I et Il. (375-345). 50 Litrae. Tête d&apos;Apollon laurée à g., les <lb/>
cheveux retombant sur la nuque. Derrière, tête de cheval. R/. SVPAK/OEIQN.Trépied. (B.M.C. <lb/>

253 p. 183). El. 3 g 60. Légères griffes au revers. Très Beau. <lb/>


*t9 -Règne de Gélon. (485-479). Tétradrachme. Quadrige au pas à d. Niké volant à d., couronne les <lb/>
chevaux. R/. LVRAKOL/IO/N. Tête d&apos;Aréthuse à d., un collier de perles dans les cheveux ramassés <lb/>

sur la nuque. Au pourtour quatre dauphins. (Boehringer R. 78, V. 51). 17 g 33. Style archaïsant. <lb/>

Très Beau. <lb/>

*20 -Démocratie. (450-439). Tétradrachme. Même type varié. R/. SVPAKOXION. Tête d&apos;Aréthuse à <lb/>

d., les cheveux couverts du saccos orné d&apos;une grecque. Ampyx lauré sur le front, collier autour <lb/>

du cou. Dauphins au pourtour. (Bo. R. 442, V. 326 -Br. 389). 16 g 83. Légèrement décentré. <lb/>

Très Beau. <lb/>

*21 <lb/>

Après la défaite des Athéniens. (405-317). Tétradrachme. Quadrige au galop à g. Au-dessus, une <lb/>

triquêtre. A l&apos;exergue : 2YPAKOSION et dessous monogramme. R/. Tête d&apos;Aréthuse à <lb/>

g., couronnée de roseaux, les cheveux relevés. Elle porte collier de perles et boucle d&apos;oreilles. Au <lb/>
pourtour trois dauphins. Sous le cou, traces des lettres N I. (Du Chastel 96 -J. 861). 17 g 14. <lb/>

Très Beau à Superbe. <lb/>

*22 -Restitution de la démocratie. (215-212). Statère. Tête d&apos;Athéna à g., coiffée du casque corinthien <lb/>

à aigrette, les cheveux retombant sur la nuque, derrière, monogramme AT. R/. Foudre. Au-dessus : <lb/>
...YPAKOLION; au-dessous : LO. (B.M.C. 655 p. 223 -Du C. 139). 6 g 83. Superbe. <lb/>

ZEUGITANE <lb/>

*23 -CARTHAGE. (300-260). Shekel. Tête de Perséphone à g., couronnée d&apos;épis, les cheveux relevés. <lb/>
Elle porte un collier et boucle d&apos;oreilles. R/. Cheval debout à d. regardant à g. Palmier et étoile. <lb/>
(M. 108 p. 89 -Jenkins et Lewis pl. 26, 17). 7 g 20. Très Beau. <lb/>

*24 -(200-146). Tétradrachme serratus. Même type varié. R/. Cheval marchant à d. Au-dessus, symbole. <lb/>

(M. 123 p. 91). 12 g 80. Presque Très Beau. <lb/>


GRÈCE CONTINENTALE <lb/>

*25 -ROYAUME DE MACEDOINE. PHILIPPE Il. (359-336). Statère. Tête laurée d&apos;Apollon à d. <lb/>
les cheveux courts. Derrière : A. R/. Bige au galop à d. conduit par un personnage drapé, tenant <lb/>

un fouet. Dessous, un foudre vertical. A l&apos;exergue : &lt;1&gt;IAIIIIIOY. (Müller 1 var. -Bab. IV, 859 <lb/>
et pl. CCCVI, 2. Pella). Or. 8 g 60. Beau style. Très Beau. <lb/>

*26 -ALEXANDRE III LE GRAND. (336-323). Statère. Tête d&apos;Athéna à d. coiffée du casque corin-<lb/>
thien à triple aigrette, orné d&apos;un serpent. R/. Niké drapée debout à g. tenant une stylis et une cou-<lb/>
ronne. Devant, corne d&apos;abondance, étoile et monogramme. (M. 381. Thrace méridionale). Or. <lb/>

8 g 53. Haut relief. Très Beau à Superbe. <lb/>

*27 -Tétradrachme. Tête d&apos;Héraclès imberbe à d. coiffée de la peau de lion nouée sous le menton. R/. <lb/>

AAEEANAPOY. Zeus aëtophore demi-nu, assis à g., s&apos;appuyant sur un sceptre. Dans le champ, <lb/>

inscription en phénicien. (M. 1430 var. -S.N.G. Lockett 1452 var.). AcePtolemais. 17 g 17. <lb/>
Haut relief. Très Beau. <lb/>

*28 -Tétradrachme. Mêmes types variés. R/. Dans le champ, protomé de bêlier. Sous le siège, A A. <lb/>
(M. 1339. -S.N.G. Lockett 1451 var.). Damas. 16 g. 98. Quelques rayures. T.B. <lb/>

*29 -Tétradrachme. (Vers 180). Mêmes types variés. R/. Dans le champ : 1 O. (M. 1185. Pourrait être <lb/>

attribué à Phaselis). 16 g 51. Flan large. Très Beau. <lb/>

*30 -ANTIGONE Il GONATAS. (277-239). Tétradrachme. Tête de Poseidon à d. couronnée d&apos;algues, <lb/>
les cheveux retombant sur la nuque. R/. BASIAEQS ANTIFONOY écrit sur une proue de navire <lb/>

à g. Sur celle-ci, Apollon nu assis à g., tenant son arc. Dessous, monogramme. (P. 968 -Br. 715 <lb/>
-S.N.G. Lockett 1527). Amphipolis ou Pella, 258-239, peut être jusque 220 sous Antigone Doson. <lb/>
17 g. Très Beau. <lb/>


*31 -PERSEE. (178-168). Tétradrachme. Tête de Persée barbue et diadémée à d. R/. Aigle debout à <lb/>
d. sur un foudre, les ailes éployées. Dans le champ, monogrammes et BASI/AEQZriEP/SEOS <lb/>
Le tout dans une couronne de chêne. (Br. 720 var. -J. 1013 var.). 15 g 34. Très Beau. <lb/>

32 -Tétradrachme. Mêmes types, monogrammes variés. (Br. 720 var. -J. 1013 var.). 13 g 96. Flan <lb/>
fracturé et recollé. B./T.B. <lb/>

*33 -MACEDOINE SOUS LA DOMINATION ROMAINE. (158-149). Tétradrachme. Bouclier macé-<lb/>
donien orné de croissants et d&apos;étoiles. Au centre, buste d&apos;Artémis à d., les cheveux relevés, des <lb/>
mèches retombant sur la nuque. R/. Massue et MAKEAONQN/nPDTHS dans une couronne <lb/>

de chêne. (B.M.C. 2 p. 7 -Br. 730). 16 g 42. Très Beau. Bien centré. <lb/>

y* <lb/>

*34 -AESILLAS, QUAESTOR. (93-92). Tétradrachme. CAE. PR. MAKELlONON. Tête d&apos;Alexandre <lb/>
le Grand à d., avec les cornes d&apos;Ammon, les cheveux flottant. A g. : @. R/. AESILLAS Q. Massue, <lb/>
entre une caisse d&apos;argent et une chaise de Questeur. Le tout dans une couronne d&apos;olivier. (B.M.C. <lb/>

81 var. p. 19 -Coll. De Luynes 1728). 16 g 76. Eclat du flan. Très Beau. <lb/>

*35 -(92-88). Tétradrachme. MAKEAONQN à l&apos;avers. Mêmes types. (B.M.C. 81 p. 19 -S.N.G. <lb/>
Lockett 1543). 16 g 56. T.B./Très Beau. <lb/>

*36 <lb/>

THRACE. VILLES DU SUD. MARONEE. (400-350). Statère. Cheval bridé, au galop à g. Tri-<lb/>
dent à g. R/. EIH/EYII/OAI/OS. Au centre, un carré linéaire contenant un cep de vigne avec quatre <lb/>

grappes. (B.M.C. 21 var. p. 125 -S.N.G. Lockett 1199 var. -P. 1047). Il g 24. T.B. à Très <lb/>

Beau. <lb/>

*37 -ABDERE. (408-350). Statère. EHI/IIAYSANIÇ2. Griffon couché à g., les ailes droites. R/. ABLlHPI/ <lb/>
TEON. Tête laurée d&apos;Apollon à d., les cheveux courts. (B.M.C. 53 p. 72 -S.N.G. Lockett 1146 <lb/>
var.). 10 g 16. T.B. à Très Beau. Rare. <lb/>

*38 <lb/>

ROYAUME DE THRACE. LYSIMAQUE. (323-281). Tétradrachme. Tête divinisée d&apos;Alexandre <lb/>
le Grand, cornue, diadémée à d. ; les cheveux ondulés flottent au vent. R/. BASIAEQS/AISIMAXOY. <lb/>
Athéna nicéphore drapée et casquée, assise à g., s&apos;appuyant sur son bouclier. Dans le champ, <lb/>
monogramme composé des lettres H P. A l&apos;exergue, monogramme. (Müller 353 -Br. 823 var! <lb/>

Héraclée). 16 g 92. T.B. à Très Beau. <lb/>

*39 -Tétradrachme. Mêmes types, monogramme varié. (M. voir 552 -Br. voir 831). 15 g 54. T.B. <lb/>


*40 -ILES DE THRACE. THASOS. (Après 146). Tétradrachme. Tête de Dionysos imberbe à d., <lb/>
diadémée et couronnée de lierre, les cheveux relevés en torsade derrière la tête, quelques mèches <lb/>

sur la nuque. R/. HPAKAEOYL/LOTHPOL/8ALION.Héraclès nu, lauré de face, s&apos;appuyant <lb/>

sur sa massue, la peau de lion sous le bras. <lb/>
dans le champ. (B.M.C. 74 p. 223 -S.N.G. Lockett <lb/>
1242). 16 g 56. Flan large. Très Beau. <lb/>

*41 <lb/>

COTE NORD-OUEST DE L&apos;EUXIN. APOLLONIA PONTICA. (450-400). Drachme. Ancre. <lb/>

Dans le champ, A et un crustacé. R/. Gorgoneion entouré de serpents. (B.M.C. Mysie 8. p 8 -<lb/>
P. 1142). 3 g 34. Très Beau. <lb/>

*42 -THESSALIE. CONFEDERATION. (196-146). Double victoriat. Tête de Zeus à d., couronnée <lb/>
de chêne. R/. 0ESSA/AQN. Athéna Itonia à d., casquée et armée du bouclier et de la lance. Au-<lb/>
dessus et au-dessous : ...AEI/TITIO... et rOprOTIAL. (B.M.C. 13 p. 2 -S.N.G. Lockett 1620var.). <lb/>

5 g 66. Très Beau. <lb/>

*43 -Drachme. Tête laurée d&apos;Apollon à d. R/. 0ES2A/(...). Même type; au-dessus, une étoile et dans <lb/>

le champ, T M. (B.M.C. 40 var. p. 4 -S.N.G. Lockett 1625 var.). 4 g 08. T.B. à Très Beau. <lb/>

*44 -LARISSA. (430-400). Drachme. Thessalos nu, le pétasse et la chlamyde flottant au vent, retenant <lb/>
un taureau qui bondit à g. Trait d&apos;exergue. R/. AAP/I/IAL. Cheval bridé au galop à d., la lanière <lb/>
flottant. (B.M.C. 33 var. p. 27 -S.N.G. Lockett 1564 var.). 6 g 06. Très Beau. Bien centré. <lb/>

*45 -BEOTIE. THEBES. (426-395). Statère. Bouclier béotien.0 dans une échancrure. R/. Tête barbue, <lb/>

couronnée de lierre de Dyonisos à d. De chaque côté : 0 et E. (B.M.C. 58 p. 74 -S.N.G. <lb/>
Lockett 1743). Il g 98. Beau style. Très Beau. <lb/>


*46 -EUBEE. CHALCIS. (369-336). Drachme. Tête de femme à d., les cheveux relevés. R/. AAX. Aigle <lb/>
debout à d., les ailes éployées, tenant un serpent. A g., un monogramme. (RM.C. 64 p 112 -<lb/>

J. 1169 var.). 3 g 40. T.B. Rare. <lb/>

*47 -ATTIQUE. ATHENES. (480-407). Tétradrachme. Tête d&apos;Athéna à d., les cheveux arrangés en <lb/>
bandeau sur les tempes. Pendants d&apos;oreilles ronds. Le casque est orné de feuilles d&apos;olivier et d&apos;une <lb/>
branche fleuronnée. R/. A@E. Chouette à d., la tête de face, les yeux globuleux. A g., pousse d&apos;olivier <lb/>
et croissant. Carré creux. (Bab. III, 1). 16 g 81. Très Beau. <lb/>

*48 -Tétradrachme. Mêmes types de style varié. (Bab. III, 2). 17 g 06. Eclat du flan. T.B. <lb/>

*49 -(178-177). Tétradrachme.Nouveau style. Tête d&apos;Athéna casquée à d. R/. A@E XAPI-HPA. Chouette <lb/>
debout de face sur une amphore. Dans le champ à d., coq et palme. A l&apos;exergue : TIP. Au pourtour, <lb/>
une couronne d&apos;olivier. (M. Thompson 130 var.). 16 g 77. T.B. <lb/>

*50 -(124-123). Tétradrachme. Mêmes types variés. R/. A@E SENOKAHS-APMOEENOi:. Sur l&apos;am-<lb/>
phore : M, dessous : IIP. (M. Th. 1101). 16 g 18. T.B./Très Beau. <lb/>

*51 -CORINTHE. (386-307). Statère. Pégase volant à g. Dessous : ? <lb/>

. <lb/>

R/. Tête d&apos;Athéna à g., coiffée <lb/>
du casque corinthien couronné. Derrière, aegis, sous le menton : A. Sous la tranche du cou -P. <lb/>

(Ravel 1009 -B.M.C. 253 p. 26). 8 g 51. Très Beau. <lb/>

*52 -Statère. Même type. R/. Tête d&apos;Athéna à g., coiffée du casque corinthien. Sous le menton : A. <lb/>

Derrière la nuque, un casque thessalien. (R. 1040 -B.M.C. 220 p. 22). 8 g 40. T.B. <lb/>

*53 -PELOPONNESE. ELIDE. (Vers 300 av. J.-C.). Statère. Tête laurée de Zeus Olympien à d. R/. <lb/>
(F)/A/A/PI. Aigle debout à d. Derrière, un foudre. Devant, une plume et une couronne. (Seltman <lb/>

227 -B.M.C. 120 var. p. 71). 12 g 07. Bien centré. Très bel exemplaire. Rare. <lb/>

*54 -(Vers 330 av. J.-C.). Quart de statère. Tête laurée de Zeus Olympien à d. R/. F -A. Aigle debout <lb/>
à d. sur un chapiteau ionien. (B.M.C. 83 p. 67 -S.N.G. Lockett 2414). 2 g 67. T.B. Rare. <lb/>


*55 -CRETE. GORTYNE. (430-300). Statère. Europe demi-nue, assise sur un arbre à d., un aigle <lb/>
éployé sur les genoux; elle cherche à se couvrir la poitrine de sa draperie. R/. Taureau debout à <lb/>

d., se tournant à g. (Svoronos 83 -Le Rider 140 -S.N.G. Lockett 2559). 10 g 86. T.B. Rare. <lb/>

*56 -(200-67). Drachme. Tête barbue et diadémée de Zeus ou de Minos à d. R/. Homme debout de <lb/>

face, tenant une haste et appuyé sur un bouclier. Derrière : rOPTYNI... Dans le champ, A. (Sv. <lb/>

147 -B.M.C. 55 var. p. 44). 3 g 26. Très Beau. <lb/>

ASIE MINEURE <lb/>

*57 -BITHYNIE. PRUSIAS 1. (238-183). Tétradrachme. Tête de Prusias barbue et diadémée à d. R/. <lb/>

BA^IAEOE/riPOY^IOY. Zeus demi-nu debout à g., s&apos;appuyant sur un sceptre et couronnant <lb/>

le nom du roi. Dans le champ, foudre, monogrammes M E et AN. (B.M.C. 2 var. p. 209 -J. <lb/>

1387 var.). 16 g 99. Beau portrait. Très Beau. <lb/>

*58 -MYSIE. PARIUM. (350-300). Tétrobole. Masque de Gorgone de face, entouré de serpents. R/. <lb/>

...A/PI. Taureau debout à g., détournant la tête. (B.M.C. 14 p. 95 -Bab. II, 2581). 2 g 42. Superbe. <lb/>

*59 -Tétrobole. Mêmes types. Mais au R/. IIA/PI. Croissant sous le taureau. (B.M.C. 21 p. 96 -Bab. <lb/>

1l, 2581). 2 g 34. Superbe. <lb/>

*60 -EOLIDE. CYME. (Après 190). Tétradrachme. Tête de Cymé à d., une bandelette dans les cheveux <lb/>
relevés. R/. KYMAIQN. Cheval bridé au pas à d.; devant, un vase à une anse. A l&apos;exergue : <lb/>
KAAAIAS. Le tout dans une couronne de laurier. (B.M.C. 73 p. 111 -S.N.G. Lockett 2745). <lb/>
16 g 66. Très Beau à Superbe. <lb/>

*61 -Tétradrachme. Mêmes types, mais au nom de : MHTPOOANHS.(B.M.C. 74 p. 111 -S.N.G. <lb/>

Lockett 2746). 16 g 81. Très Beau à Superbe. <lb/>


*62 -MYRHINA. (Après 189). Tétradrachme. Tête d&apos;Apollon laurée à d., les cheveux retombant sur <lb/>
la nuque. R/. MYPINAIQN. Apollon demi-nu, marchant à d., tenant une patère et un rameau <lb/>
de laurier enguirlandé. A ses pieds, l&apos;omphale et diota. Dans le champ, monogramme des lettres <lb/>

B T N. (B.M.C. 7 p. 136). 16 g 94. Superbe. <lb/>

*63 <lb/>

LESBOS. MYTILENE. (550-440). Didrachme. Deux têtes de veaux affrontées, séparées par une <lb/>
tige d&apos;olivier chargée de feuilles et de fruits. R/. Carré creux. (Bab. 1, 607 -S.N.G. Von Aulock <lb/>

1682). Bill. 11 g 04. Très Beau. <lb/>

*64 -IONIE. EPHESE. (394-295). Tétradrachme. E &lt;D. Abeille volant, vue de dos. R/. IAEOL. Protomé <lb/>
de cerf à demi agenouillé à d., détournant la tête; derrière, un palmier. (B.M.C. 30 sq. var. p. 51 <lb/>
-Bab. II, 1883 var.). 14 g 61. Coup au revers. Eclat du flan. Très Beau. <lb/>

*65 -Tétradrachme. Mêmes types, mais au nom de : BAOLQN. (B.M.C. 30 sq. var p 51 -Bab II <lb/>

1883). 14 g 48. T.B. <lb/>

*66 <lb/>

MAGNESIE DU MEANDRE. (Après 190). Tétradrachme. Buste d&apos;Artémis diadémé et drapé <lb/>

à d., l&apos;arc et le carquois dépassant derrière la nuque. R/. A d. : MArNHTON.A g. : EY&lt;DHMOLI <lb/>

ITAYSANIOY. Apollon nu, debout à g., tenant une guirlande, s&apos;appuyant à un trépied surmonté <lb/>
d &apos;un carquois. A l&apos;exergue, une base méandroïde. Au pourtour, une couronne de laurier. (B.M.C, <lb/>

36 p. 162). 16 g 95. Très Beau. <lb/>

*67 -Tétradrachme. Mêmes types, mais au nom de : nAYEANIAE/HAYSANlOY. (B.M.C. 36 var. <lb/>

p. 162 -S.N.G. Von Aulock 7922). 16 g 95. Très Beau. <lb/>

*68 <lb/>

PHOCEE. (480-334). Hecté. Tête de femme à g. (Ménade?), les cheveux retenus par un bandeau <lb/>
-autour duquel sont enroulées des torsades de cheveux; de petites bandelettes noueuses descendent <lb/>

des tempes. R/. Carré creux. (B.M.C. 57 p. 211 -Bab. II, 2110). El. 2 g 49. Très Beau à Superbe. <lb/>


*69 -CARIE. ALABANDA. (Après 168). Tridrachme. Tête laurée d&apos;Apollon à d., les cheveux relevés, <lb/>

deux mèches tombant sur la nuque. R/. AAABAN/AEQN. Pégase au galop à d., devant : IA; <lb/>
le tout dans une couronne de laurier. (B.M.C. 10 var. p. 2 -S.N.G. Von Aulock 2385 var.). <lb/>
11 g 72. Flan déformé. Très Beau. Très Rare. <lb/>

*70 -ILES DE CARIE. RHODES. (407-333). Didrachme. Tête d&apos;Hélios de face, tournée à d., les che-<lb/>

veux au vent. R/. Rose sur sa tige avec un bouton à d. Dans le champ à g., E et grappe de raisin. <lb/>
(B.M.C. 27 var. p. 233 -S.N.G. Von Aulock 2790 var.). 6 g 57. Haut relief. Légère corrosion <lb/>
à l&apos;avers. De très beau style. Très Beau. <lb/>

*71 -(333-304). Didrachme. Même type, mais tête d&apos;Hélios radiée. R/. POAION. Rose sur sa tige avec <lb/>
un bouton à d. A g., une harpé et E Y. (B.M.C. 53 p. 235). 6 g 62. Bien centré. T.B. <lb/>

*72 -(304-166). Didrachme. Même type. R/. MNAZIMAXOY. Rose sur sa tige avec un bouton à d. <lb/>
De chaque côté : P -O. A g., Athéna debout à g. (B.M.C. 143/145 var. p. 244). 6 g 66. T.B./Très <lb/>

Beau. <lb/>

*73 -(166-88). Drachme. Tête d&apos;Hélios radiée à d. R/. AESIKPATH2. Rose avec branche à d. De <lb/>

chaque côté : P -o. A g., une araignée suspendue à son fil. (B.M.C. 256 var. p. 254). 3 g 01. T.B. <lb/>

*74 -LYDIE. (625-561). Trité. Tête de lion à d. R/. Carré creux. (B.M.C. 6 p. 2 -S.N.G. Von Aulock <lb/>
2868). El. 4 g 40. Très Beau. Rare. <lb/>

*75 -TRALLES. (133-126). Cistophore. Serpent se glissant hors de la cyste mystique, le couvercle sou-<lb/>
levé. Le tout dans une couronne de lierre. R/. Deux serpents. A g. : B/TPAA, au-dessus : IITOA. <lb/>
A. d. Dionysos tenant un masque et un thyrse. (B.M.C. 45 p. 332). 12 g 47. Très Beau à Superbe. <lb/>

*76 -LYCIE. DYNASTES. THETHIVEIBIS. (480-460). Statère. Tête d&apos;Aphrodite à g., les cheveux <lb/>

retenus par des bandelettes et relevés en chignon. R/. TiXXEF&apos; EBE. Tétraskèle et inscription <lb/>

dans un carré creux. (B.M.C. 89 var. p. 19 -Bab. 11, 330, pl. XCVIII, 17 var.). 9 g 89. T.B./Très <lb/>
Beau. Rare. <lb/>

*77 -SPINTAZA. (470-450). Statère. Même type. R/. SITETAIAA. Même type. (B.M.C. 96 var. p. 21 <lb/>

-Bab. II, 337 var.). 9 g 77. T.B. à Très Beau. Rare. <lb/>

*78 -PAMPHYLIE. ASPENDOS. (394-300). Statère. Deux lutteurs se tenant par les poignets. Entre <lb/>
les deux : IIO. R/. EETFEAIIY. Un frondeur à d. Entre ses jambes : K. Devant, triquètre. (B.M.C. <lb/>
56 var. p. 100). 10 g 81. Très bel exemplaire. <lb/>


*79 -CILICIE. CELENDRIS. (400-350). Statère. Ephèbe assis de face sur son cheval, galopant à g. <lb/>
R/. Bouquetin agenouillé à g., détournant la tête. Au-dessus : KEAEN. (B.M.C. 11 var. p. 53 <lb/>

Bab. II, 1472 sq. var.). 10 g 72. Très Beau. <lb/>

*80 -SOLI. (Vers 400). Statère. Archer à demi agenouillé à g., tenant son arc. Il a un jupon autour <lb/>
des reins et un carquois suspendu à son côté. R/. SOAEQN. Grappe de raisin avec une longue <lb/>
vrille à d. Dans le champ, croix ansée, (A) et O. (B.M.C. 6 p. 145 -Bab. II, 546). 10 g 24. T.B. <lb/>

à Très Beau. <lb/>

*81 -ROIS DE SYRIE. ANTIOCHUS VII EVERGETE. (138-129). Tétradrachme. Buste diadémé et <lb/>
drapé d&apos;Antiochus VII à d. R/. BA2IAEQ2/ANTIOXOY. Aigle debout à g. sur un éperon de <lb/>
navire, avec une palme appuyée sur son aile. Dans le champ, massue et APE à g., monogramme <lb/>

et COP à d. A l&apos;exergue, monogramme. (B. 1072 var.). Tyr, COP = 176. 13 g 88. Très Beau. <lb/>

*82 -ALEXANDRE II ZEBINA. (128-123). Tétradrachme. Tête diadémée d&apos;Alexandre II à d. R/. <lb/>
BASIAE^S/AAESAN APOY. Zeus demi-nu, assis à g. sur un trône à dossier. Il tient une petite <lb/>
Victoire et s&apos;appuie sur un long sceptre. Dans le champ et sous le siège, monogrammes. A l&apos;exer-<lb/>

gue : qp. (B. 1277 var. -B.M.C. 4 var. p. 81). qp = 190. 16 g 51. Beau portrait. Très Beau à <lb/>

Superbe. <lb/>

*83 -Tétradrachme. Mêmes types et légende, mais au R/., monogrammes variés. (B. voir 1275 -B.M.C. <lb/>

voir 4 p. 81). 15 g 94. Presque Très Beau. <lb/>

*84 -SELEUCIDE ET PIERIE. SELEUCIE. (IIe et Ier siècles). Tétradrachme. Buste tourelé de Tyché <lb/>
à d. Bandelette de laine au pourtour. R/. SEAEVKEQN/THSIEPAS/KAI/AYTONOMOY. Foudre <lb/>
orné du bandeau royal sur un trône. Entre les pieds : ZI. A d., monogramme. (B.M.C. 23 var. <lb/>

p. 271 -J. 1765 var.). An 16 de l&apos;autonomie = ZI. 14 g 31. Flan large. Très Beau à Superbe. <lb/>

*85 -PHENICIE. ARADOS. (Vers 380). Statère. Tête barbue et laurée de Melkarth. R/. Galère voguant <lb/>
à d. et inscription en phénicien. Carré creux. (B.M.C. A/. 19 et R/. 18 p. 4-5 -S.N.G. Lockett <lb/>

3206). 10 g 49. T.B. <lb/>

*86 -(350-332). Statère. Mêmes types variés. L&apos;inscription occupe tout le champ au-dessus de la galère <lb/>
(B.M.C. 62 p. 10). 10 g 67. T.B./Très Beau. <lb/>

*87 -SIDON. ABDASTORET II. (373-362). Double shekel. Galère voguant, comme ci-dessus. Au-<lb/>

dessus, le chiffre IIII (an 4). R/. Le roi de Perse dans son char à g., suivi d&apos;un personnage. Lettres <lb/>

90 dans le champ. (B.M.C. 29 var. p. 145 -Bab. II, 918). 24 g 31. T.B. <lb/>

*88 -JUDÉE. JERUSALEM. 1&quot; révolte. (66-70). Shekel. An 2. Légendes en hébreu. (Shekel d&apos;Israël). <lb/>

Calice, au-dessus : (an 2). R/. (Jérusalem la sainte). Rameau à trois boutons. (Reifenberg 139 <lb/>
-B.M.C. 7 p. 270). 14 g 19. Superbe. <lb/>

*89 -ROIS DE PARTHIE. MITHRIDATE 1. (171-138). Drachme. Buste d&apos;Arsacès 1, imberbe, casqué <lb/>

et diadémé à g. R/. BAHIAEQX/APSAKOY.Arsacès vêtu d&apos;une armure, assis à d. sur l&apos;omphalos. <lb/>

(Sellwood 9, 1). Ecbatane? 3 g 82. Très Beau. <lb/>

*90 -MITHRIDATEII. (123-88). Drachme. Buste du roi barbu, cuirassé et diadémé à g. R/. BAL/AEOLI <lb/>

MErAAOY/AR}:AKOY/ETII&lt;DANOY}:. Même type varié. (S. 26, 1). Ecbatane? 3 g 48. Très <lb/>

Beau à Superbe. <lb/>

*91 -ROIS DE PERSE. DARIUS Il NOTHUS. (424-405). Darique. Le roi à demi-agenouillé à d., coiffé <lb/>
de la cidaris et vêtu de la candys. Il tient son arc de la main g. et sa javeline de la d. Sur le dos, <lb/>
un carquois. R/. Carré creux rectangulaire. (B. Les Perses Achéménides 64, pl. II, 1 -Bab. II, 7). <lb/>

Or. 8 g 33. Très Beau. Rare. <lb/>

*92 -Sicle. Mêmes types. (Bab. 11, 8-9 -B.M.C. 56-57 p. 155). 5 g 58. T.B. à Très Beau. <lb/>

*93 -ROIS DE BACTRIANE. AZILISES. (Vers 40-25). Tétradrachme. BASIAEQ^BA^IAEQN <lb/>
MErAAOY AZIAISOY. Le roi à cheval à d., tenant de la main d. l&apos;ankus. R/. Même légende <lb/>
en prâcrit. Femme drapée à g., tenant une palme et un bouquet (?). Devant, monogramme. <lb/>
(B.M.C. 7 sq. var. p. 94 -S.N.G. Lockett 3377 var.). 9 g 60. Très Beau à Superbe. <lb/>



MONNAIES ROMAINES ET BYZANTINES <lb/>

(en or sauf indication contraire) <lb/>

*94 -EMPIRE ROMAIN. <lb/>

AUGUSTE. (27 aV.-14 ap. J.-C.). Aureus. CAESAR AVGVSTVS DIVI F PATER PATRIAE. <lb/>
Tête d&apos;Auguste laurée à d. R/....CAESARES/AVGVSTI F COS DESIG PRI... Caïus et Lucius <lb/>
debout, tenant une haste et un bouclier. Dans le champ, simpule et bâton d&apos;augure. (Roman <lb/>
Imperial Coinage 350 p. 90 -Giard 1648 sq. -Cohen 42). Lyon, 2 av.-14 ap. 7 g 79. Très Beau. <lb/>

*95 -TIBERE. (14-37). Aureus. TI CAESAR DIVI/AVG F AVGVSTVS. Tête de Tibère laurée à d. <lb/>
R/. PONTIF MAXIM. Livie ou la Paix assise à d., tenant une haste et une branche. (R.I.C. 3 <lb/>
p. 103 -C. 15). Lyon. 7 g 68. Très beau portrait. Superbe. <lb/>

*96 -Aureus. Autre exemplaire, de coins variés. (R.I.C. 3 p. 103 -C. 15). Lyon. 7 g 86. Très Beau. <lb/>

97 -HADRIEN. (117-138). Sesterce. HADRIANVS/AVG COSIII PP. Buste barbu et lauré à d. R/. <lb/>
SALVS AVG. La Santé debout à g., tenant une haste et nourrissant un serpent sur un autel. De <lb/>
chaque côté : S-C. (R.I.C. 786 p. 440 -C. 1333). Rome, 134-138. Br. 25 g 19. Patine brune. Très <lb/>

Beau. <lb/>

*98 -ANTONIN LE PIEUX. (138-161). Aureus. ANTONINVS AVG/PIVS PP TRPXVI. Tête d&apos;An-<lb/>

tonin laurée à g. R/. COS 1111. Antonin debout à g., tenant un globe dans la main d. (R.I.C. 226f <lb/>
p. 53 -C. 307). Rome, 152-153. 7 g 33. Petite entaille sur la tranche. Très Beau. <lb/>

*99 -MARC AURELE. (César 139-161 -Auguste 161-180). Aureus. AVRELIVS CAE/SAR AVG PII <lb/>
FIL. Buste de Marc Aurèle drapé et cuirassé à d. R/. TRPOT VII COSII. Rome casquée, debout <lb/>

à g., tenant une Victoire dans la main d. et un parazonium de la g. (R.I.C. 457b p. 85 -C. 660 <lb/>

var.). Rome, 152-153. Frappé sous Antonin. 7 g 11. Flan irrégulier. Très Beau. <lb/>

*100 -JULIA DOMNA. (Ep. Septime Sévère). Aureus. IVLIA. DO/MNA. AVG. Buste drapé de Julie <lb/>
à d., les cheveux ramenés derrière la nuque. R/. VENERI VICTR. Vénus demi-nue, debout à d., <lb/>
tenant une pomme et une palme, appuyée sur une colonne. (R.I.C. 536 p. 165 -C 193). Rome, <lb/>
193-196. 7 g 08. Superbe. <lb/>

*101 -CONSTANCE II. (César 324-337 -Auguste 337-361). Solidus. CONSTANTI/VS AVGVSTVS. <lb/>
Buste de Constance II, diadémé, drapé et cuirassé à d. R/. VICTORIAE DD NN AVGG. Vic-<lb/>
toire assise à d. sur une cuirasse, écrivant : VOT/XX/MVLT/XXX sur un bouclier que lui présente <lb/>
un génie ailé. A l&apos;exergue : SMAQ. Couronne de laurier au pourtour. (C. 288). Aquilée. 4 g 38. <lb/>

Superbe. <lb/>

*102 <lb/>

GRATIEN. (367-383). Solidus. DN GRATIA/NVS PFAVG. Buste de Gratien, diadémé, drapé <lb/>
et cuirassé à d. R/. VICTORIA AVGG. Gratien et Valentinien jeunes, assis de face, soutenant <lb/>
un globe. Entre eux, une Victoire à mi-corps. En bas, une palme. A l&apos;exergue : COM. (C. 38). <lb/>
Thessalonique. 4 g 46. Traces et défauts de la tranche. T.B. <lb/>

*103 -EMPIRE BYZANTIN. <lb/>

CONSTANTIN IV avec ses frères HERACLIUS ET TIBERE. (668-680). Solidus. Buste barbu <lb/>
casqué et cuirassé de face de Constantin IV tenant une lance sur l&apos;épaule. R/. Croix sur trois degrés, <lb/>
entre Héraclius et Tibère. (Ratto 1649 -Morrisson 9 p. 379). Constantinople, officine E. 4 g <lb/>

34. <lb/>

Très Beau à Superbe. <lb/>

*104 -ROMAIN IV DIOGENE. (1068-1071). Nomisma histaménon. Michel VII entre Constantin et <lb/>
Andronic, debout de face. R/. Le Christ nimbé, debout de face, couronnant Romain et Eudoxie. <lb/>
(R. 2026 var. -M. 1 var. p. 649). Constantinople. 4 g 31. T.B./Très Beau. <lb/>


MONNAIES GAULOISES <lb/>

*105 -ANDECAVI. (Anjou). Statère. Tête d&apos;Ogmius à d., avec un cordon perlé aboutissant à trois <lb/>
petites têtes. Un rayon sur la tête. R/. Cheval androcéphale à d. Dessous, une figure à mi-corps. <lb/>
(La Tour 6728). Or natif. 7 g 52. Beau portrait. Très Beau. Variété rare. <lb/>

*106 -AULERCI CENOMANI. (Région du Mans). Statère. Tête d&apos;Ogmius à d., une mèche de cheveux <lb/>
isolée sur le front. R/. Androcéphale ailé à d. L&apos;aurige tient le vexillum. Sous le cheval, une figure <lb/>
couchée. (LT. 6858 var.). Or cuivré. 6 g 97. B./T.B. à T.B. <lb/>

*107 -BAIOCASSES. (Région de Bayeux). Statère. Tête d&apos;Ogmius à d., entourée de cordons de perles. <lb/>
R/. Androcéphale à d. L&apos;aurige tient le vexillum. Sous le cheval, un sanglier. (LT. 6967-6969 var.). <lb/>

Arg. 7 g 15. T.B <lb/>

*108 -BOII DE LA TRANSPADANE. Tétradrachme. Tête imberbe, diadémée à g. Le diadème est figuré <lb/>
par trois rangs de grénetis et les cheveux par deux rangs de palmes. R/. Cheval à g. (LT. -F-). <lb/>

Arg. 11 g 01. T.B. <lb/>


MONNAIES FRANÇAISES <lb/>

*109 -LOUIS IX. (1226-1270). Gros tournois. 1266. LVDOVICVS. REX entre deux grénetis. Légende <lb/>

extérieure. Croix au centre. R/. TVRONVS-CIVIS. Châtel surmonté d&apos;une croix. En bordure, <lb/>

12 fleurs de lis, celle du haut accostée de deux points. (Lafaurie 198 a -Hoffmann-). Arg. 4 g <lb/>

14.&apos; <lb/>

Très Beau. <lb/>

*110 -PHILIPPE IV LE BEL. (1285-1314). Gros tournois à 1&apos;0 rond. + PhILIPPVS REX. Même type. <lb/>

R/. Mêmes légende et type varié. (L. 217 -H. 5). Arg. 4 g 06. Superbe. <lb/>

*111 <lb/>

PHILIPPE VI DE VALOIS. (1328-1350). Royal d&apos;or. A partir de 1328. Le roi tenant un long <lb/>

sceptre, debout sous un dais gothique avec contreforts, s&apos;avançant sur une marche ornée de sau-<lb/>
toirs. R/. Croix fleuronnée dans un quadrilobe cantonné de quatre couronnelles. (L. 251 -H. 1). <lb/>

Or. 4 g 22. Superbe. <lb/>

*112 -Royal d&apos;or. Annelet après la croisette du R/. (L. 251 -H. 1). Or. 4 g 20. T.B. <lb/>

*113 -Ecu d&apos;or. 3e émission. 5 Janvier 1348. Le roi assis sur un trône gothique, tenant l&apos;épée et appuyé <lb/>

sur l&apos;écu aux fleurs de lis sans nombre. Au pourtour sauf à l&apos;exergue, polylobe cantonné de trèfles. <lb/>

R/. x après la croisette initiale. Croix fleuronnée dans un quadrilobe cantonné de quatre trèfles. <lb/>
(L. 262 b -H. 3 var.). Or. 4 g 47. Exemplaire de belle qualité. <lb/>

*114 -Ecu d&apos;or. 5e émission, x après la croisette du R/. (L. 262 b -H. 3 var.). Or. 4 g 47. T.B. à Très <lb/>

Beau. <lb/>

*115 -Ecu d&apos;or. 4e émission. 13 Août 1348. Variantes de ponctuation, x après la croisette du R/. <lb/>
Deux des trèfles du R/. entre deux annelets. (L. 262 c -H. 3 var.). Or. 4 g 48. T.B. à Très Beau. <lb/>

*116 -JEAN II LE BON. (1350-1364). Mouton d&apos;or. 17 Janvier 1355. Agneau Pascal nimbé deb. à g., <lb/>
détournant la tête vers une croix fleuronnée à longue hampe où flotte une bannière, dans un poly-<lb/>
lobe orné de trèfles, interrompu à l&apos;exergue. R/. Croix fleuronnée, cantonnée de quatre lis, dans une <lb/>
rosace à quatre lobes et quatre pointes. (L. 294 -H. 3). Or. 4 g 63. Flan large. Très Beau. <lb/>

*117 -Franc à cheval. 5 Décembre 1360. Le roi à cheval, au galop à g., armé de toutes pièces et coiffé <lb/>

d&apos;un heaume, tenant la bride et l&apos;épée. R/. Croix fleuronnée dans une rosace quadrilobée et can-<lb/>

tonnée de quatre trèfles. (L. 297 -H 10). Or. 3 g 82. Très Beau. <lb/>

*118 -CHARLES V. (1364-1380). Franc à pied. 20 Avril 1365. Le roi debout sous un dais à pinacle, <lb/>
tenant l&apos;épée et la main de justice. Champ semé de lis. R/. Croix fleuronnée, cantonnée de deux <lb/>
lis et de deux couronnelles dans une rosace à quatre lobes et quatre pointes. (L. 371 var. -H. 2 <lb/>

var.). Or. 3 g 76. Très Beau. <lb/>


*120 -Ecu à la couronne. 1re ou 2e émission. (L. 378 -H. 1). Or. 4 g. Très Beau. <lb/>

*121 -Ecu à la couronne. Point creux apparaissant faiblement sous la lre lettre de la légende au droit <lb/>

et au R/. (Voir L. 419 et Coll. Marcheville 959). Dijon, 1417-1418. Or. 3 g 66. Très Beau. <lb/>

*122 -HENRI VI. (1422-1453). Salut d&apos;or. 2e émission, 6 Septembre 1423. La Salutation angélique. <lb/>
L&apos;Ange et la Vierge Marie derrière deux écus aux armes de France et d&apos;Angleterre. R/. Croix <lb/>

latine plaine, accostée d&apos;une fleur de lis et d&apos;un léopard. Au-dessous, h; le tout dans un polylobe. <lb/>

(L. 447 a -H. 2). Paris. Or. 3 g 50. Flan large. Superbe. <lb/>

*123 -Salut d&apos;or. 2e émission. (L. 447 a -H. 2). Rouen. Or. 3 g 47. Superbe. <lb/>


123A-CHARLES VII. (1422-1461). Royal d&apos;or. 1&quot; émission. Le roi debout, vêtu d&apos;une longue robe et <lb/>

d&apos;un manteau, tenant deux sceptres, sur un champ fleurdelisé. R/. Croix fleuronnée dans une <lb/>
rosace quadrilobée, cantonnée de quatre couronnelles. (L. 459-H. 9). Angers. Or. 3 g 90. T.B. <lb/>

*124 -LOUIS XI. (1461-1483). Demi-écu au soleil. A partir du 2 Novembre 1475. Ecu couronné, sommé <lb/>

d&apos;un soleil flamboyant. R/. Croix fleurdelisée. (L. 530 -H. 2). Toulouse, 1475-1483. Or.&apos; <lb/>

1 g 80. <lb/>

Très Beau. Rare. <lb/>

124A -LOUIS XII. (1498-1515), Ecu dor au soleil de Provence 3e type. novembre 1499. Même typ s, <lb/>
légendes variées. En fin de légendes : ToLo. (L. 596 b -H. 3 var. -Collection Marcheville 2089). <lb/>

Tarascon. Or. 3 g 34. T.B. <lb/>

*125 <lb/>

FRANÇOIS Ier. (1515-1547). Ecu au soleil. 2e type. Ecu de France .couronné, surmonté d&apos;un <lb/>

soleil. R/. Croix fleurdelisée, cantonnée de deux F couronnés. (L. 636 -H. 2). Lyon, 1515-1519. <lb/>

Or. 3 g 40. Très Beau. <lb/>

*126 -Teston. 10e type. Buste imberbe du roi, vêtu de la cuirasse, coiffé de la couronne fermée. R/. Ecu <lb/>
de France couronné, accosté de deux F couronnés. (L. 667 -H. 42). Lyon, 1528-1529. Arg. 9 g 27. <lb/>

Très Beau. <lb/>

*127 -Teston. 10e type. (L. 667 -H. 42). Lyon, 1529-1531. Arg. 9 g 15. T.B. <lb/>

*128 -HENRI II. (1547-1559). Double Henri d&apos;or. 1er type. HENRICVS. Il. D.G. FRAN. REX. Point <lb/>
sous la septième lettre. Buste du roi à d., barbu, tête nue, vêtu de la cuirasse. R/. DVM. TOTVM. <lb/>
COMPLEAT. ORBEM. R. 1553. (3 regravé sur 1). Point sous la septième lettre et petit point <lb/>

sous le 0 de TOTVM. Croix formée de quatre H couronnés, cantonnée de deux croissants et de <lb/>

deux fleurs de lis. Au centre, différent d&apos;atelier. (L. 809 -H. 26). Toulouse, 1553. (M.m. Jehan Robert). <lb/>
Or. 7 g 25. Beau portrait de frappe excellente. Très Beau à Superbe. Rare. <lb/>

*129 -FRANÇOIS II ET MARIE STUART. Monnaie Franco-Ecossaise. Gros d&apos;argent. Ecu couronné, <lb/>

parti de France et d&apos;Ecosse, accosté d&apos;une croix plaine et d&apos;une croix de Saint André. R/. Dans <lb/>
le champ, FM liés et couronnés, accostés d&apos;un lis et d&apos;un chardon non couronnés. (H. 3 var. -<lb/>

C. 1338 var.). 1560. Arg. 6 g 05. Léger éclat du flan. Très Beau. Variété rare sans couronne au-<lb/>
dessus du lis et du chardon. Peut-être inédit. <lb/>

*130 -CHARLES IX. (1560-1574). Double Henri d&apos;or au nom d&apos;Henri II. Ier type. HENRICVS. II. <lb/>

D.G. FRAN. REX. Point sous la quinzième lettre. Buste du roi à d., barbu, tête nue, vêtu de la <lb/>
cuirasse. R/. DVM. TOTVM. COMPLEAT. ORBEM. (Calice) 1561. Point sous la quinzième <lb/>
lettre. Croix formée de quatre H couronnés, cantonnée de deux croissants et de deux fleurs de <lb/>
lis. Au centre différent d&apos;atelier. (L. 873 -H. -). Rouen, 1561. (M.m. Nicolas Delisle). Or. 7 g 23. <lb/>
Quelques manques dus à la frappe. Très Beau. Rare. <lb/>


*131 -Ecu d&apos;or. Il&quot; type. Ecu de France timbré d&apos;une couronne fermée. Date en fin de légende. R/. Croix <lb/>

fleurdelisée. Au centre, différent d&apos;atelier. (L. 890 -H. 1). Angers, 1574. Or. 3 g 36. T.B. à Très <lb/>

Beau. <lb/>

*132 -Ecu d&apos;or du Dauphiné. Ecu écartelé de France-Dauphiné, timbré de la couronne fermée. R/. Même <lb/>

croix. Z au centre; en fin de légende : 1567. D : marque du maître Pierre de Luan. (L. 893 -<lb/>
H. 4). Grenoble, 1567. Or. 3 g 17. Presque Très Beau. Rare. (Environ 1 200 pièces frappées en 1567). <lb/>

*133 -LOUIS XIII. (1610-1643). Louis. Tête laurée à d. Longues mèches de cheveux descendant sur <lb/>

le cou. R/. Croix formée de huit L couronnés et cantonnée de quatre lis. Différent d&apos;atelier en <lb/>

coeur. (H. 22 var. -C. 1613 var.). Paris, 1641. Or. 6 g 65. Très Beau. <lb/>

*134 -Demi-Louis. Mêmes types. (H. 24 var. -C. 1615 var.). Paris, 1642. Or. 3 g 38. Très Beau à Superbe. <lb/>

*135 -Demi-Louis. (H. 24 var. -C. 1615 var.), Paris, 1642. Or. 3 g 35. Très Beau. <lb/>

*136 -30 Sols. Deuxième poinçon de Warin. Buste lauré, cuirassé et drapé à d. R/. Ecu couronné. Rose <lb/>
en début de légende. (H. 94 -C. 1665 var.). Paris, 1643. Arg. 13 g 58. Superbe. <lb/>

*137 -15 Sols. Mêmes types. Même rose initiale au R/. (H. 97 var. -C. 1666 var.). Paris, 1642. Arg. 6 g 75. <lb/>
Très Beau à Superbe. <lb/>

*138 -LOUIS XIV. (1643-1715). Louis à la mèche courte. Tête enfantine, laurée à d., les cheveux courts. <lb/>
Dessous, date. R/. Huit L adossés et couronnés, disposés en croix et cantonnés de quatre lis. (H. 6 -<lb/>
C. 1781). Paris, 1644. Or. 6 g 76. Très Beau à Superbe. <lb/>

*139 -Louis à la mèche longue. Tête enfantine, laurée à d., les cheveux longs. R/. Même type. (H. 12 -<lb/>
C. 1787). Angers, 1649. Or. 6 g 70. Très Beau à Superbe. Date rare. <lb/>

*140 -Louis à la mèche longue. (H. 12 -C. 1787). Paris, 1649. Or. 6 g 74. Très Beau/T.B. <lb/>

*141 -Louis juvénile lauré. Tête juvénile, laurée à d., les cheveux en boucles sur le cou. Dessous, la date. <lb/>

R/. Même type. (H. 22 -C. 1789). Aix, 1672. Or. 6 g 72. Très Beau. <lb/>


*143 -Louis juvénile à la tête nue. Mêmes types. Coiffure variée. (H. 24 var. -C. 1791 var.). Lyon, 1671. <lb/>

Or. 6 g 75. Flan large. Très Beau à Superbe. <lb/>

*144 -Louis juvénile à la tête nue. Coiffure variée. (H. 26 var. -C. 1793 var.). Paris, 1675. Or. 6 g 73. <lb/>

Traces de griffes. T.B. <lb/>

*145 -Louis aux quatre L. Tête âgée, laurée, avec grande perruque, à d. Dessous, date. R/. Croix formée <lb/>
de quatre lis couronnés, cantonnée de quatre L. Au centre, dans un cercle, différent d&apos;atelier. <lb/>
(H. 33 -C. 1801). Poitiers, 1692. Réformation. Or. 6 g 42. Sauf coup sur la tranche, Superbe. <lb/>

*146 -Louis aux quatre L. (H. 33 -C. 1801). Bourges? 1696. Réformation. Or. 6 g 78. Traces de surfrappes. <lb/>

T.B. <lb/>

*147 -Demi-écu à la mèche longue. Buste enfantin à d., lauré et cuirassé, une mèche de cheveux des-<lb/>
cendant le long du cou. R/. Ecu couronné. Point initial. (H. 76 -C. 1850). Toulouse, 1652. Arg. <lb/>

13 g 62. Très Beau. <lb/>

*148 -Ecu au buste juvénile. Buste jeune, lauré et drapé, avec longue perruque, à d. R/. Ecu couronné. <lb/>
(H. 102 -C. 1862). Aix, 1666. Arg. 27 g 20. Léger manque du flan au revers. Très Beau. <lb/>

A l&apos;avers, la reproduction montre un point dans le champ qui n&apos;existe pas sur la pièce. <lb/>

149 -Demi-écu au buste juvénile. Mêmes types. (H. 105 -C. 1863). Montpellier, 1668. Arg. 13 g 53. <lb/>

Egratignures dans le champ à l&apos;avers et sur les bords. Quelques retouches. T.B. Rare. <lb/>

*150 -Demi-écu Carambole. Buste drapé à d., avec grande perruque. R/. Ecu couronné, écartelé de France-<lb/>
Bourgogne. Date en fin de légende. (H. 129 -C. 1885). Paris, 1685. Arg. 18 g 60. Très Beau à Superbe-<lb/>


*152 -Ecu aux trois couronnes. Buste cuirassé, avec grande perruque, à d. R/. Trois couronnes en triangle, <lb/>
séparées par trois lis. Différent d&apos;atelier au centre. (H. 187 -C. 1937). Paris, 1709. Arg. 30 g 36. <lb/>
Petit coup sur la tranche. Presque Très Beau. <lb/>

*153 -Demi-écu aux trois couronnes. Mêmes types. (H. 189 -C. 1938). Paris, 1710. Arg. 15 g 23. Sauf <lb/>
légères rayures, Superbe. <lb/>

*154 -Dixième d&apos;écu aux trois couronnes. Mêmes types. (H. 191 -C. 1940). Pau, 1714. Arg. 2 g 43. B./ <lb/>

T.B. à T.B. Rare. <lb/>

*155 -Trente Sols. Fleur de lis florencée. R/. Dans le champ, en trois lignes. XXX./. SOLS./. 1684. (H. <lb/>
275 -C. 2049). Strasbourg, 1684. Arg. 14 g 78. Très Beau. <lb/>

*156 -Demi-écu aux insignes. Ecu rond couronné, posé sur un sceptre et une main de justice. R/. Grand <lb/>
lis épanoui. (H. 283 -C. 2057). Strasbourg, 1702. Réformation. Arg. 15 g. T.B. <lb/>


*158 -Louis aux lunettes. Buste jeune, drapé à g. R/. Sous une couronne, deux écus ovales penchés, aux <lb/>
armes de France et de Navarre. (H. 16 -C. 2085). Paris, 1726. Or. 8 g 18. Très Beau. <lb/>

*159 -Louis aux lunettes. (H. 16 -C. 2085). Bayonne, 1728. Or. 8 g 13. Presque Superbe. <lb/>

*160 -Louis aux lunettes. (H. 16 -C. 2085). Lyon, 1728. Or. 8 g 15. Très Beau. <lb/>

161 -Louis aux lunettes. (H. 16 -C. 2085). Orléans, 1728. Or. 8 g 16. Très Beau. <lb/>

*162 -Demi-louis aux lunettes. Mêmes types. (H. 17 -C. 2086). Rennes, 1729. Or. 4 g 02. Rayures au <lb/>

revers. T.B. <lb/>

*163 -Louis au bandeau. Buste plus âgé à g. la tête ceinte d&apos;un bandeau. R/. Même type. (H. 19 -C. 2088). <lb/>

Lille, 1745. Or. 8 g 15. Superbe/Très Beau. <lb/>

*164 -Louis au bandeau. (H. 19 -C. 2088). Paris, 1747. Or. 8 g 18. Superbe/Très Beau. <lb/>

*165 -Louis au bandeau. (H. 19 -C. 2088). Paris, 1753. Or. 8 g 18. Très Beau à Superbe. <lb/>

*166 -Ecu Vertugadin. Buste enfantin, drapé, à d. Dessous, une rose. R/. Ecu rond couronné. (H. 27 -<lb/>
C. 2096). Lille, 1716. Réformation. Arg. 30 g 20. T.B. à Très Beau. <lb/>

*167 -Petit louis d&apos;argent. Buste un peu plus âgé, lauré, drapé et cuirassé à d. Dessous, millésime. R/. <lb/>
Quatre double L couronnés et posés en croix. Au centre, différent d&apos;atelier. (H. 33 -C. 2136). <lb/>
Amiens, 1720. Arg. 8 g 07. Superbe/Très Beau. <lb/>

*168 -Ecu de Navarre. Buste lauré et drapé à d. R/. Ecu couronné, écartelé de France et Navarre. (H. 34 -<lb/>
C. 2101). Amiens, 1719. Arg. 24 g 30. T.B./Très Beau. <lb/>


169 -Ecu de Navarre. (H. 34 -C. 2101). Perpignan, 1718. Arg. 24 g 02. Seule année pour cet atelier. <lb/>

B./T.B. <lb/>

*170 -Ecu de France. Buste lauré et drapé à d. R/. Ecu couronné. (H. 40 -C. 2107). Tours, 1721. Réfor-<lb/>
mation. Arg. 24 g 52. Manques de métal au revers. Très Beau. <lb/>

*171 -Ecu aux huit L. Buste lauré et cuirassé à d. R/. Quatre lis disposés en croix; autour, quatre double L <lb/>

et quatre couronnes. Dessous, différent d&apos;atelier. (H. 45 -C. 2112). Rennes, 1725. Arg. 23 g 30. <lb/>
Quelques rayures. Très Beau à Superbe. <lb/>

*172 -Demi-écu aux huit L. Mêmes types. (H. 46 -C. 2113). Paris, 1725. Arg. 11 g 67. Petite craquelure <lb/>
sur le cou. Très Beau. Rare. <lb/>


173 -Demi-écu aux huit L. (H. 46 -C. 2113). Rouen, 1725. Arg. 11 g 68. B. Rare. <lb/>

-Demi-écu aux lauriers. Buste cuirassé à g. Croix et cordon du Saint-Esprit sur la poitrine. R/. Ecu <lb/>
ovale couronné, entre deux branches de laurier. (H. 51 -C. 2118). Rouen, 1732. Arg. 14 g 50. T.B. <lb/>

*175 -Petit écu de trois livres au bandeau. Tête à g., ceinte d&apos;un bandeau. R/. Même type. (H. 58 -C. 2125). <lb/>

La Rochelle, 1762. Arg. 14 g 51. Très Beau. <lb/>

*176 -LOUIS XVI. (1774-1793). Ecu aux lauriers. Buste à g., avec plaque et cordon du Saint-Esprit. <lb/>

R/. Même type. (H. 11 -C. 2187). Limoges, 1784. Arg. 29 g 20. Très Beau à Superbe. <lb/>

177 -Petit écu aux lauriers. Mêmes types. (H. 13 -C. 2189). Paris, 1783. Arg. 14 g 25. Coup sur le côté <lb/>
du flan à l&apos;avers. T.B. <lb/>

*178 -Ecu de six livres de la période constitutionnelle. Buste du roi à g. R/. Génie de la Constitution. <lb/>
(Mazard 5). Bayonne, 1793. Arg. 29 g 29. Très Beau. <lb/>

179 -Ecu de trois livres, 30 et 15 sols. Mêmes types. (M. 9, 13, 17). Paris, 1793. Lille, 1793. Paris, 1791. <lb/>

Arg. 14 g 62, 10 g 10, 5 g 09. Ens. 3 p. B., T.B., le dernier Superbe. <lb/>

-REVOLUTION. Monnaie de confiance. 5 sols des frères Monneron. Hercule rompant le faisceau. <lb/>
R/. REVOLUTION FRANÇAISE 1792. Dans le champ : MEDAILLE/QUI SE VEND/CINQ -<lb/>
SOLS/A PARIS CHEZ/MONNERON/(PATENTÉ). (M. 163). Paris, 1792. Br. 28 g. Superbe. <lb/>

*181 -LA CONVENTION. (1792-1795)..24 livres. Génie de la France gravant la Constitution. Faisceau <lb/>
avec bonnet à g. Coq à d. R/. Valeur et différent d&apos;atelier dans une couronne de feuillage. (M. 250). <lb/>
Paris, An II, 1793. Or. 7 g 60. Rayures. T.B. Rare. <lb/>

*182 -Six livres. Mêmes types variés. (M. 251). Paris, An II, 1793. Arg. 29 g 55. Très Beau. <lb/>

183 -Demi-sol. Table accostée d&apos;une grappe et d&apos;épis. R/. Couronne fermée et balance avec bonnet. <lb/>

(M. 260). La Rochelle, 1793. Mdc. -Décime. Buste de la République à g. R/. Valeur et date <lb/>

dans une couronne. (M. 265). Paris, l&apos;An 4. Cu. Ens. 2 p. Très Beau à Superbe. Le premier Rare. <lb/>

*184 -Essai de fabrication par Galle. Buste de la Liberté à g., pique et bonnet. Sur la tranche du buste, <lb/>
signature : GALLE. R/. A LA/CONVENTION/NATIONALE/PAR LES/ARTISTES REUNIS/ <lb/>

DE LYON.7 PUR METAL/DE CLOCHE/FRAPPEEN/MDCCXCII. (M. 318 a). Lyon, 1792. <lb/>

Mdc. Flan double épaisseur. Sauf encoche au revers, Superbe. <lb/>

*185 -REPUBLIQUE SUBALPINE. (1800-1802). 20 Francs. Buste casqué, lauré et drapé de la Répu-<lb/>
blique à g. R/. Valeur et millésime dans une couronne de laurier. (Pagani 3 p. 59). Turin, An 9. <lb/>

Or. Très Beau à Superbe. <lb/>

*186 -CONSULAT. BONAPARTE. (1799-1804). 40 Francs. Tête nue à g. R/. Valeur dans une couronne <lb/>
de laurier. (M. 403). Paris, An 12. Or. Très Beau. <lb/>

*187 -5 Francs. Tête nue à d. R/. Même type. (M. 435). Paris, An XI. Arg. Très Beau à Superbe. <lb/>

-EMPIRE. NAPOLEON Ier. (1804-1815). 20 Francs. Tête nue à g. R/. Valeur dans une couronne <lb/>
de laurier. (M. 417). Paris, An 12. Or. Très Beau. <lb/>

*189 -5 Francs. Tête nue à d. R/. Même type. (M. 438). Paris, An 13. Arg. Coup sur la joue. Léger manque <lb/>
sur le bord au revers. Très Beau. <lb/>

-2 Francs. Mêmes types. (M. 454 b). Paris, An 13. (3 sur 2). Arg. T.B. <lb/>

*191 -NAPOLEON Ier ROI D&apos;ITALIE. (1805-1814). 40 Lire. Tête nue à g. R/. Armoiries couronnées. <lb/>

(P. 15 a p. 79). Milan, 1812. Or. Très Beau à Superbe. <lb/>


*192 -DUCHE DE PARME. MARIE LOUISE. (1815-1847). 40 Lire. Buste diadémé à g. R/. Armoiries <lb/>
couronnées. (P. 1 p. 136). Milan, 1815. Or. Très Beau à Superbe. <lb/>

*193 -ROYAUME D&apos;ESPAGNE. JOSEPH NAPOLEON. (1808-1814). 20 Reales. Tête nue à g. R/. <lb/>

Ecu couronné, accosté de la valeur. (Vicenti 5421). Madrid, 1811. Arg. Presque Superbe. <lb/>

*194 -ROYAUME DE WESTPHALIE. JEROME NAPOLEON. (1807-1813). 2/3 de thaler. Tête laurée <lb/>

à d. R/. Valeur dans le champ. (V.G. 1970 -Jaeger 17 c). Clausthal, 1813. Arg. Superbe. <lb/>

*195 -CAPITULATION DE PARIS. (30-31 Mars 1814). ALEXANDRE 1er EMPEREUR DE RUSSIE. <lb/>

Module de 5 Francs. GALLIA REDDITA EUROPAE. APRILE 1814. Dans le champ, trois <lb/>

fleurs de lis dans un globe. R/. AU PACIFICATEUR DE L&apos;EUROPE. A et 1 dans le champ. <lb/>

(M. 766 a). Paris, 1814. Arg. Superbe. <lb/>


*196 -FRANÇOIS Ier EMPEREUR D&apos;AUTRICHE. Module de 5 Francs. Même type. R/. ANGE/ <lb/>

DE/PAIX. (M. 769). Paris, 1814. Arg. Très Beau à Superbe. <lb/>

*197 -FREDERIC GUILLAUME III ROI DE PRUSSE. Module 5 Francs. Mêmes types. (M. 771). <lb/>

Paris, 1814. Arg. Superbe. <lb/>

*198 -LOUIS XVIII. Second gouvernement royal. (8 Juillet 1815 -16 Septembre 1824). 40 Francs. Tête <lb/>
nue à d. R/. Ecu couronné entre deux branches de laurier. (M. 649). Lille, 1818. Or. Très Beau. <lb/>

*199 -5 Francs. Tête nue à g. R/. Même type varié. (M. 671). Rouen, 1818. Arg. Superbe. <lb/>

*200 -CHARLES X. (1824-1830). 40 Francs. Tête nue à d. R/. Ecu couronné entre deux branches de <lb/>
laurier. (M. 807). Paris, 1828. Or. Quelques légères rayures à l&apos;avers. Très Beau à Superbe. <lb/>

201 -2 Francs. Tête nue à g. R/. Même type. (M. 827). Strasbourg (17 713 ex.), Lille, 1829. Arg. Ens. <lb/>

2 p. T.B. <lb/>

202 -Franc, Demi-franc. Mêmes types. (M. 833, 838). Lille, 1829. Paris, 1828. Arg. Ens. 2 p. Superbe. <lb/>

203 -HENRI V PRETENDANT. Franc, Demi-franc. (M. 911, 914). 1831, 1833. Arg. Ens. 2 p. Superbe. <lb/>


*204 -LOUIS PHILIPPE. (1830-1848). 2 Francs. Tête couronnée de chêne à d. R/. Valeur et date dans <lb/>

une couronne de feuillage. (M. 993). Rouen, 1844. 12 527 exemplaires. Arg. Superbe. Rare. <lb/>

*205 -Franc. Tête nue à d. R/. Même type varié. (M. 998). Paris, 1831. Arg. Superbe. <lb/>

206 -Francs. Tête couronnée de chêne. (M. 1004, 1005). Paris, 1837. Rouen, 1838. Arg. Ens. 2 p. Superbe. <lb/>

*207 -SECOND EMPIRE. NAPOLEON III. (1852-1870). 100 Francs. Tête nue à d. (M. 1407). Paris, <lb/>

1857. Or. Très Beau à Superbe. <lb/>

*208 -100 Francs. Tête laurée. (M. 1414). Paris, 1865. 1 517 exemplaires. Or. Très Beau à Superbe. <lb/>

Rare. <lb/>

*209 -100 Francs. (M. 1415 a). Strasbourg, 1866. 3 075 exemplaires. Or. Presque Superbe. Rare. <lb/>

*210 -100 Francs. (M. 1417). Paris, 1868. 2 315 exemplaires. Or. Presque Superbe. Rare. <lb/>

*211 -100 Francs. (M. 1417 a). Strasbourg, 1868. Quelques exemplaires. Or. Presque Superbe. Très <lb/>

Rare. <lb/>


*212 -50 Francs. Tête laurée. (M. 1430). Paris, 1866. Or. Très Beau à Superbe. <lb/>

*213 -CHAMBRE DE COMMERCE DE LILLE. Visite de LL. MM. II. A LA BOURSE. Tête nue <lb/>

à g. (M. 1752 a). 1853. Module 27. Arg. Superbe. <lb/>

*214 -FRAPPE DU SOUVENIR. NAPOLEON IV. *Essai de 20 Centimes. (M. 1767). 1874. Arg. -<lb/>
ESSAI D&apos;OUTILLAGE. Essai par la firme Uhlhorn de Cologne pour proposition d&apos;outillage <lb/>
à la Monnaie de Paris. (V.G. 2986 -M. 1166 a var.). Tr. en français. 1846. Br. Ens. 2 p. F.D.C. <lb/>

*215 -TROISIEMEREPUBLIQUE. (1870-1940). 100 Francs. Le Génie de la France gravant la Consti-<lb/>

tution. R/. Valeur dans une couronne de chêne. (M. 1774). Paris, 1886. Or. Très Beau à Superbe. <lb/>

*216 -100 Francs. (M. 1792). Paris, 1912. Or. Presque Superbe. <lb/>

*217 -100 Francs par Bazor. Effigie de la République à g., coiffée d&apos;un bonnet ailé. R/. Valeur dans les <lb/>
rayons d&apos;un soleil levant. Epi entre deux rameaux d&apos;olivier et de laurier. (M. 2345). 1935. Or. <lb/>

Superbe. <lb/>


armé de toutes pièces, brandissant une epee et tenant un ecu orne de trois mouchetures a nermine, <lb/>
galopant à d. sur un cheval caparaçonné. R/. Croix ornementée, cantonnée de quatre mouchetures, <lb/>

dans un entourage à quatre lobes et quatre pointes. (Poey d&apos;Avant 1256 var.). Nantes. Or. 2 g 85. <lb/>

Très Beau à Superbe. Rare. <lb/>

*219 -ARCHEVECHE D&apos;ARLES. ETIENNE DE LA GARDE. (1351-1359). Florin. Grand lis épanoui. <lb/>
R/. Saint Jean Baptiste bénissant d&apos;une main et tenant une croix de l&apos;autre. Différent, croix en-<lb/>

grêlée. (P.A. 4106 var.). Or. 3 g 46. Très Beau à Superbe. <lb/>

*220 -PRINCES D&apos;ORANGE. RAYMOND III (1335-1340) ou RAYMOND IV (1340-1393). Florin. <lb/>

Mêmes types variés. Différent : casque. (P.A. 4521). Or. 3 g 49. Très Beau à Superbe. <lb/>

*221 -DAUPHINS DE VIENNOIS. CHARLES V, dauphin de France. (1349-1364). Florin. Mêmes types <lb/>
variés. Différent : tour. (P.A. 4894). Or. 3 g 46. Très Beau. <lb/>

*222 -DUCHE DE BRABANT. JEANNE ET WENCESLAS. (1355-1383). Mouton d&apos;or. Dans un poly-<lb/>
lobe, Agneau Pascal debout à g., nimbé, détournant la tête vers une croix fleurdelisée à longue <lb/>
hampe où flotte une bannière. Dessous : IOh&apos;/DYX. R/. Croix feuillue, cantonnée de quatre lis, <lb/>
dans un encadrement formé de quatre lobes et de quatre angles, (de Witte 387 -Delmonte 43). <lb/>
Or. 4 g 56. Flan large. Presque Superbe. <lb/>

*223 -HOLLANDE. PHILIPPE LE BON. (1425-1428). Chaise d&apos;or. Dans un polylobe, le comte assis <lb/>

sur un siège gothique, tenant l&apos;écu de Bourgogne. R/. Croix ornementée dans un quadrilobe. (Del. <lb/>
738). Or. 3 g 60. Bel exemplaire. <lb/>


MONNAIES ETRANGERES <lb/>

*224 -ALLEMAGNE. BURGRAVES DE FRIEDBERG. HANS EITEL DIEDE. (1671-1685). Gulden. <lb/>

Saint Georges terrassant le dragon. De part et d&apos;autre, écus de Friedberg et de Kaichen. R/. Aigle <lb/>

bicéphale couronné, soutenant le globe crucigère. Dessous, écus du Burgrave et de son épouse. <lb/>
(Reimmann 5032). Arg. 19 g 46. Très belle iconographie. Très Beau. <lb/>

*225 -ANGLETERRE. HENRI VI. (1422-1461). Noble. Le roi couronné, tenant l&apos;épée et l&apos;écu, debout <lb/>
de face, à mi-corps dans une nef. R/. Croix fleuronnée, cantonnée de quatre léopards couronnés, <lb/>

dans un polylobe cantonné de trèfles et d&apos;un annelet. (North 1414 -Seaby 1207). Londres, 1422-<lb/>

1427. Or. 6 g 90. Flan large. Très Beau à Superbe. <lb/>

*226 -GEORGES III. (1760-1820). Demi-guinée. Tête laurée, cheveux courts, à d. R/. Armes couronnées. <lb/>

Autour, devise de l&apos;ordre de la Jarretière. (S. 2964). 1809. Or. Presque Superbe. <lb/>

*227 -GEORGES VI. (1936-1952). Proof du Demi-souverain. Tête à g. R/. Saint Georges. (S 3305). <lb/>
1937. Or. F.D.C. Rare. <lb/>

*228 <lb/>

ESPAGNE. FERDINAND ET ISABELLE. (1474-1504). Deux excelentes. Bustes affrontés et <lb/>

couronnés des souverains. Entre les deux, S. Au dessus, symbole entouré de quatre points. R/. Aigle <lb/>
soutenant un écu couronné. (Caries -Tolra 1139 var.). Séville. Or. 6 g 97. Très Beau. <lb/>

*229 -PHILIPPE II. (1555-1598). 4 Escudos. Ecu couronné, accosté d&apos;une part d&apos;un S et de 1111, de <lb/>
l&apos;autre de la date. R/. Croix potencée dans un quadrilobe. (Vicenti -Lopez Chavès -Vidal Quadras -<lb/>

C.T.-). Séville, 1592. Or. 13 g 46. Flan irrégulier. Très Beau. Rare. <lb/>

*230 -CHARLES III. (1760-1788). 8 Escudos. Buste drapé et cuirassé à d. Dessous, date. R/. Armes <lb/>

couronnées, entourées du collier de l&apos;ordre de la Toison d&apos;Or et accostées de 8 -S. (V. 3931). <lb/>

Séville, 1788. Or. 26 g 97. Très Beau. <lb/>

*231 -FERDINAND VII. (1808-1833). 8 Escudos. Buste lauré à d. Dessous, date. R/. Même type. (V <lb/>

6831). Mexico, 1815. Or. 26 g 97. T.B. <lb/>

*232 <lb/>

ITALIE. ROYAUME DE SICILE. MESSINE. FREDERIC II. (1197-1250). Demi-augustale. <lb/>
Buste lauré et drapé à l&apos;antique à d. R/. Aigle debout, de face, détournant la tête à d. (Revue Suisse <lb/>

de Numismatique 1976 p. 128, pl. 3, A. 82. -Friedberg voir 135 p. 262). Or. 2 g 45. Traces de <lb/>
monture. B./T.B. Rare. <lb/>

*233 -SAVOIE. LOUIS Ier. (1434-1465). Ducat d&apos;or. Le duc heaumé, brandissant l&apos;épée en main d., <lb/>
galopant à d. sur un cheval caparaçonné. R/. Ecu aux armes de Savoie, lambrequiné et heaumé, <lb/>
accosté de F C -R T. Le tout dans une rosace à quatre lobes et quatre pointes. (C.N. I. ,i, 14 var. <lb/>

p. 65 -Promis pl. VII, 1 var.). Or. 3 g 46. Très Beau à Superbe. Rare. <lb/>

*234 -SAVOIE -SARDAIGNE. CHARLES ALBERT. (1831-1849). 100 Lire. Tête nue à g. Dessous, <lb/>

date. R/. Armes couronnées, entourées du collier de l&apos;ordre de l&apos;Annonciade et de deux branches <lb/>

de laurier. (P. 139 p. 10). Turin, 1834. Or. 32 g 22. Très Beau à Superbe. <lb/>

235 -MONACO. RAINIER III. (1949-). Série de 4 pièces. Essais en argent de 100, 50, 20 et 10 Francs <lb/>
(15 g, 10 g, 6 g 5, 3 g 8). Effigie à g. du Prince Rainier III, gravée par Turin. R/. Pour les pièces <lb/>
de 100 et 50 Francs, cavalier galopant à d. sur un cheval caparaçonné, protégé par un boucliel <lb/>
aux armes du Prince de Monaco et brandissant une lance. R/. Pour les pièces de 20 et 10 Francs, <lb/>
écusson couronné du Prince. (Voir Yeoman, 16, 15, 14, 13 p. 328). Paris, 1950. Arg. Ens. 4 p. <lb/>
F.D.C. <lb/>



236 -Série de 4 pièces. Essais en piedfort d&apos;argent de 100, 50, 20 et 10 Francs. (30 g, 20 g, 13 g, 7 g 6). <lb/>
Mêmes types. (Voir Y. 16, 15, 14, 13 p. 328). Paris, 1950. Arg. Ens. 4 p. F.D.C. <lb/>

*237 -SUISSE. SOLEURE. Demi-duplone. Ecu couronné aux armes du canton, orné d&apos;une guirlande. <lb/>
R/. Saint en armes, debout de face, un drapeau en main d. (Divo 673 p. 194). 1787. Or. 3 g 80. <lb/>
Presque Superbe. Rare. <lb/>

*238 -LUCERNE, 4 Franken. Ecu ovale couronné, aux armes du canton, entre deux palmes. Dessous, <lb/>

date. R/. Guerrier debout, coiffé d&apos;un chapeau à plumes, tenant une hallebarde en main d. et posant <lb/>
la main g. sur un écu portant : XIX/CANT. Dessous, valeur. (D. 53 p. 40). 1814. Arg. 29 g 37. Très <lb/>

Beau à Superbe. <lb/>

*239 -ETATS UNIS. 10 Dollars. Tête de la Liberté à d. R/. Aigle, armes et devise. (Y. p. 178 -F. 70). <lb/>
1801. Or. Très Beau à Superbe. Rare. <lb/>

*240 <lb/>

ORIENT LATIN. BAUDOUIN Ier (1100-1118). Imitation du Besant Sarracénat des Khalifes <lb/>

Fatimides. Quatre lignes d&apos;écriture pseudo-coufique, entourées d&apos;un double cercle puis d&apos;une <lb/>

légende en même caractères. Quatre annelets entre les deux cercles. R/. Même type varié. (Schlum-<lb/>

berger p. 134, Type 1 var.). Or. 3 g 10. Presque Superbe. <lb/>

*241 -ETHIOPIE. ENDYBIS. (Vers 300 av. J.-C.). Demi-aureus. Buste casqué et drapé à d., entre <lb/>

deux épis. R/. Même description. (F. 1 p. 93). Or. 2 g 70. Superbe. <lb/>

*242 -INDE. MYSORE. HAIDAR ALI. (1761-1782). Pagode. Civa et Parvati assis de face. R/. Croissant <lb/>
sur un champ de granulés. (Elliot 114 var. -F. 282 p. 254). Or. 3 g 40. Superbe. <lb/>

*243 -KRISHNA RAJAH WODEYAR. (1799-1868). Pagode. Même type. R/. Légende nagari en trois <lb/>

lignes. (El. 114-115. -F. 290 p. 254). Or. 3 g 40. Superbe. <lb/>

*244 -NEGAPATNAM.Pagode. Vishnu debout de face. R/. Granulés. (F. 295 p. 254). Or. 3 g 37. Superbe. <lb/>

245 -FRANCE. LOUIS XIV. Ecu à la mèche longue. Buste lauré à d. R/. Ecu couronné. (H. 74 -C. 1849). <lb/>

Nantes, 1652. Arg. 27 g 15. T.B. <lb/>

246 -LA LIGUE. Demi-franc au nom d&apos;Henri III. (L. 1002 -H. -). Toulouse, 1591. -LOUIS XIII. <lb/>

15 Sols. (H. 97 var. -C. 1666 var.). Paris, 1642. -LOUIS XIV. Quarts d&apos;écu à la mèche courte. <lb/>
(2). (H. 61 var. -C. 1835 var.). Paris, 1644, 1645. Arg. Ens. 4 p. B./T.B. <lb/>

246A -ESPAGNE. CHARLES IV. (1788-1808.) 8 Reales, (V. 4674). Mexico, 1792. -SUISSE. BERNE. <lb/>
5 Francs. (D. 300). Berne, 1924. Ens. 2 p. Arg. T.B. <lb/></body>


<front>BIBLIOGRAPHIE <lb/>

POUR LES MONNAIES GRECQUES : <lb/>

B. <lb/>

E. BABELON. Les Rois de Syrie, d&apos;Arménie et de Commagène. Paris, 1890. <lb/>

B. <lb/>

E. BABELON. Les Perses Achéménides. Paris, 1893. <lb/>

Bab. <lb/>

E. BABELON. Traité des Monnaies Grecques et Romaines. Paris, 1901-1933. <lb/>

Bo. <lb/>

E. BOEHRINGER. Die Munzen von Syrakus. Berlin-Leipzig, 1929. <lb/>

Br. <lb/>

A. B. BRETT. Catalogue of Greek Coins. Boston, 1955. <lb/>

B.M.C. <lb/>

BRITISH MUSEUM COINS. Catalogue of Greek Coins. Londres, 1873-1927. <lb/>

Du C. <lb/>

Cte A. Du CHASTEL DE LA HOWARDRIES. Syracuse. Ses monnaies d&apos;argent et d&apos;or au point <lb/>
de vue artistique. Londres, 1898. <lb/>

-<lb/>

H. HERZFELDER. Les Monnaies d&apos;argent de Rhégion. Paris, 1957. <lb/>

J. <lb/>

Collection R. JAMESON. Monnaies Grecques Antiques. Paris, 1913. <lb/>

J.L. <lb/>

G. K. JENKINS et R. B. LEWIS. Carthaginian Gold and Electrum Coins. Royal Numisma-<lb/>
tic Society. Londres, 1963. <lb/>

-<lb/>

J. BABELON. Catalogue de la collection de Luynes. Paris, 1920. <lb/>

M. <lb/>

L. MULLER. Numismatique d&apos;Alexandre le Grand. Copenhague, 1855. <lb/>

M. <lb/>

L. MULLER. Numismatique de Lysimaque. Copenhague, 1858. <lb/>

M. <lb/>

L. MULLER. Les Monnaies de l&apos;Afrique ancienne. Copenhague, 1860. <lb/>

P. <lb/>

Collection Prof. S. Pozzi. Monnaies Grecques antiques. Lucerne, 1921. <lb/>

R. <lb/>

O. E. RAVEL. Les Poulains de Corinthe. Londres, 1936. <lb/>

-<lb/>

A. REIFENBERG. Ancient Jewish Coins. 2 éd. Jérusalem, 1947. <lb/>

-<lb/>

G. LE RIDER. Monnaies crétoises du Ve au Ier siècle av. J.C. Etudes crétoises, XV, 1966. <lb/>

S. <lb/>

A. SAMBON. Les Monnaies Antiques de l&apos;Italie. Paris, 1903. <lb/>

S. <lb/>

D. SELLWOOD. Coinage of Parthia. Londres, 1971. <lb/>

-<lb/>

C. T. SELTMAN. The Temple Coins of Olympia. Cambridge, 1921. <lb/>

-<lb/>

J. N. SVORONOS. Numismatique de la Crête ancienne Mâcon, 1890. <lb/>

V. <lb/>

E. O. RAVEL. Descriptive Catalogue of the Collection of Tarentine Coins formed by <lb/>
M. P. Vlasto. Londres, 1947. <lb/>

S.N.G. <lb/>

SYLLOGE NUMMORUM GRAECORUM. <lb/>

-The Lloyd Collection. Londres, 1934-1937. <lb/>
-The Lockett Collection Londres, 1939, 1942, 1945, 1949. <lb/>
-Sammlung von Aulock. Berlin, 1962-1968. <lb/>
-Ashmolean Museum Oxford. Londres, 1962-1969. <lb/>
-Staatliche Münzsammlung München. Berlin, 1973. <lb/>

POUR LES MONNAIES ROMAINES ET BYZANTINES : <lb/>

C. <lb/>

H. COHEN. Description Historique des Monnaies frappées sous l&apos;Empire Romain. 2 éd. <lb/>

Paris, 1880-1892. <lb/>

Del. <lb/>

J.B. GIARD. Bibliothèque Nationale. Catalogue des Monnaies de l&apos;Empire Romain. <lb/>

T. I. Auguste. Paris, 1976. <lb/>

M. <lb/>

C. MORRISSON. Catalogue des Monnaies Byzantines de la Bibliothèque Nationale. <lb/>
Paris, 1970. <lb/>

R. <lb/>

R. RATTO. Catalogue des Monnaies Byzantines. Lugano, 1930. <lb/>

R.I.C. <lb/>

The Roman Imperial Coinage. Londres, 1923-1973. <lb/>

POUR LES MONNAIES GAULOISES, FRANÇAISES ET FEODALES : <lb/>

C. <lb/>

L. CIANI. Les Monnaies royales françaises de Hugues Capet à Louis XVI. Paris, 1926. <lb/>

Del. <lb/>

A. DELMONTE. Le Bénélux d&apos;or. Amsterdam, 1964. <lb/>

H. <lb/>

H. HOFFMANN. Les Monnaies royales de France depuis Hugues Capet jusqu&apos;à Louis XVI. <lb/>

Paris, 1878. <lb/>

-<lb/>

K. JAEGER. Die neueren Münzpragungen der deutschen Staaten vor Einführung der <lb/>

Rcichswahrung 1806-1871. Heft 7. Bâle, 1960. <lb/>

L. <lb/>

J. LAFAURIE et P. PRIEUR. Les Monnaies des rois de France. Paris-Bâle, 1951-1956. <lb/>

LT. <lb/>

H. DE LA TOUR. Atlas des monnaies gauloises. Paris, 1892. <lb/>

-<lb/>

(Collection de Marcheville). Catalogue de monnaies françaises de Hugues Capet à <lb/>
Henri IV. 3 parties. Vente à l&apos;amiable des 22-26 novembre 1927, 21 mai 1928, 22 avril <lb/>
1929, Paris, Florange et Ciani. <lb/>

M. <lb/>

J. MAZARD. Histoire monétaire et numismatique contemporaine. Paris-Bâle, 1965-1969. <lb/>

P. <lb/>

A. PAGANI. Monete italiane dall&apos;invasione Napoleonica ai giorni nostri. (1796-1961). Milan, <lb/>

1962. <lb/>

P.A. <lb/>

F. POEY D&apos;AVANT. Monnaies féodales de France. Paris, 1862. <lb/>

-<lb/>

A. DE WITTE. Histoire monétaire du Brabant. Anvers, 1894-1900. <lb/>


POUR LES MONNAIES ETRANGERES : <lb/>

-<lb/>

E. CARLES-ToLRA. Catalogo de la Coleccion Numismatica. Barcelone, 1936. <lb/>

C.N.I. <lb/>

CORPUS NUMMORUM ITALICORUM. Primo Tentativo di un Catalogo generale delle monete <lb/>
medievali coniate in Italia o da Italiani in altre paesi. Milan, 1910-1940. <lb/>

D. <lb/>

J. P. Divo et E. TOBLER. Die Münzen der Schweiz im 18 Jahrhundert. Zurich, 1974. <lb/>

El. <lb/>

Sir W. ELLIOT. Coins of southern India. Numismata Orientalia. Londres, 1886. <lb/>

Fr. <lb/>

R. FRIEDBERG. Gold. coins of the World. 4 éd. New York, 1976. <lb/>

-<lb/>

H. KOWALSKI. Die Augstalen Kaiser Friedrich II. RSN., 1976, p. 77 à 150. <lb/>

-<lb/>

L. LOPEZ-CHAVEZ Y SANCHEZ et J. D. YRIARTE Y OLIVA. Catalogo de la Onza. Madrid, 1961. <lb/>

N. <lb/>

J. J. NORTH. English hammered coinage. Londres, 1960. <lb/>

-<lb/>

D. PROMIS. Monete dei Reali di Savoia. Turin, 1841. <lb/>

-<lb/>

Collection REIMMANN. Munzen und Medaillen-Cabinet. Francfort, 1891-1892. <lb/>

-<lb/>

G. SCHLUMBERGER. Numismatique de l&apos;Orient Latin. Paris. 1878. <lb/></front>


<back>Imprimerie des Arts et Manufactures <lb/>
26, rue de la Glacière -75013 Paris <lb/>
70089-01-77 -Dépôt légal 1&quot;&apos;&quot; tr. 77 n°3 146 <lb/></back>















</text>
</tei>